Workbook

Sheet Read Me
A1: Debt Management Module - Features, Stories and Tasks
A2: Implementation backlog derived from Debt_Management_Maker_Checker_Approver_Design.docx. Acceptance criteria are written in strict Given-When-Then format.
A4: Backlog measure | B4: Value | D4: Workbook structure
A5: Features | B5: =COUNTA(Features!$C$5:$C$200) -> 78 | D5: Features | E5: Feature catalogue with source references, dependencies and formula-driven story/task counts.
A6: User stories | B6: =COUNTA(Backlog!$E$5:$E$1000) -> 680 | D6: Backlog | E6: One row per user story, with actor, workflow, source requirement and Given-When-Then acceptance criteria.
A7: Implementation tasks | B7: =COUNTA(Tasks!$A$5:$A$4000) -> 3100 | D7: Tasks | E7: Implementation tasks mapped to every story, including UX, API, validation, workflow, registers, integration and testing.
A8: Acceptance criteria | B8: 2933 | D8: Data Objects | E8: M01-M43 masters, C01-C13 configurations and R01-R24 registers with fields, values, triggers and actions.
A9: Master / configuration objects | B9: 56 | D9: FRS Traceability | E9: Original 43 FRS rows plus the additional loan/WMA elaborations mapped to feature and story IDs.
A10: Registers | B10: 24 | D10: Lists | E10: Controlled values used for status, priority, phase and task type.
D11: Source convention | E11: Fxx = functional workflow; ACxx = accounting workflow; Mxx/Cxx/Rxx retain the document identifiers.
A13: How to use the backlog
A14: 1 | B14: Filter Features by phase and priority to agree release scope.
A15: 2 | B15: Review each Backlog story and confirm the Given-When-Then criteria with business, accounting and technical owners.
A16: 3 | B16: Assign owners and estimates to Tasks; Status is intentionally set to Not Started.
A17: 4 | B17: Use Feature ID, Story ID and M/C/R references to trace every item back to the source document.
A18: 5 | B18: Treat Project/Program data as an existing integrated source; do not create a duplicate project master in this module.
A19: 6 | B19: Retain Maker-Checker-Approver decisions, effective versions, corrections and destination outcomes in R19/R20.

Sheet Features
A1: Feature Catalogue
A2: Functional, accounting and data-foundation features with traceability and formula-driven coverage counts.
A4: Epic Section | B4: Epic | C4: Feature ID | D4: Feature | E4: Purpose / Scope | F4: Source Section | G4: Story Count | H4: Task Count | I4: FRS Sl. Nos. | J4: Master / Config Refs | K4: Register Refs | L4: Dependencies | M4: Priority | N4: Suggested Phase | O4: Coverage
A5: 0 | B5: Data Foundation and Traceability | C5: DF01 | D5: Master data and shared-source integration | E5: Implement or integrate M01-M43 with effective dates, ownership, validations and F01 approval controls. | F5: 8-9 / 13 | G5: =COUNTIF(Backlog!$C$5:$C$684,C5) -> 43 | H5: =COUNTIF(Tasks!$C$5:$C$3104,C5) -> 215 | J5: M01, M02, M03, M04, M05, M06, M07, M08, M09, M10, M11, M12, M13, M14, M15, M16, M17, M18, M19, M20, M21, M22, M23, M24, M25, M26, M27, M28, M29, M30, M31, M32, M33, M34, M35, M36, M37, M38, M39, M40, M41, M42, M43 | L5: F01-F04, AC01, C01, R19-R20 | M5: Must | N5: 1 - Foundation and Configuration | O5: =IF(AND(G5>0,H5>0),"Covered","Gap") -> Covered
A6: 0 | B6: Data Foundation and Traceability | C6: DF02 | D6: Effective-dated configuration and control tables | E6: Implement C01-C13 as tested, versioned and approved control tables used by functions and calculations. | F6: 8-9 / 13 | G6: =COUNTIF(Backlog!$C$5:$C$684,C6) -> 13 | H6: =COUNTIF(Tasks!$C$5:$C$3104,C6) -> 65 | J6: C01, C02, C03, C04, C05, C06, C07, C08, C09, C10, C11, C12, C13 | L6: F01-F04, AC01, C01, R19-R20 | M6: Must | N6: 1 - Foundation and Configuration | O6: =IF(AND(G6>0,H6>0),"Covered","Gap") -> Covered
A7: 0 | B7: Data Foundation and Traceability | C7: DF03 | D7: Event registers, balances and traceability | E7: Implement R01-R24 as event-led registers with immutable movements, derived balances and end-to-end traceability. | F7: 8-9 / 13 | G7: =COUNTIF(Backlog!$C$5:$C$684,C7) -> 24 | H7: =COUNTIF(Tasks!$C$5:$C$3104,C7) -> 120 | K7: R01, R02, R03, R04, R05, R06, R07, R08, R09, R10, R11, R12, R13, R14, R15, R16, R17, R18, R19, R20, R21, R22, R23, R24 | L7: F01-F04, AC01, C01, R19-R20 | M7: Must | N7: 1 - Foundation and Configuration | O7: =IF(AND(G7>0,H7>0),"Covered","Gap") -> Covered
A8: 1 | B8: 1. General | C8: F01 | D8: Maintain master values | E8: Masters / source references: M01-M35; shared values remain in their owning modules. | F8: 1.5.1 | G8: =COUNTIF(Backlog!$C$5:$C$684,C8) -> 8 | H8: =COUNTIF(Tasks!$C$5:$C$3104,C8) -> 36 | J8: M01, M35 | L8: M01, M35 | M8: Must | N8: 1 - Foundation and Configuration | O8: =IF(AND(G8>0,H8>0),"Covered","Gap") -> Covered
A9: 1 | B9: 1. General | C9: F02 | D9: Configure Maker, Checker and Approver routing | E9: Masters / source references: M01, M04, M10; C01. | F9: 1.5.2 | G9: =COUNTIF(Backlog!$C$5:$C$684,C9) -> 8 | H9: =COUNTIF(Tasks!$C$5:$C$3104,C9) -> 36 | J9: C01, M01, M04, M10 | L9: C01, M01, M04, M10 | M9: Must | N9: 1 - Foundation and Configuration | O9: =IF(AND(G9>0,H9>0),"Covered","Gap") -> Covered
A10: 1 | B10: 1. General | C10: F03 | D10: Maintain exchange and interest rates | E10: Masters / source references: M04, M18, M21; C02. | F10: 1.5.3 | G10: =COUNTIF(Backlog!$C$5:$C$684,C10) -> 8 | H10: =COUNTIF(Tasks!$C$5:$C$3104,C10) -> 36 | I10: 35 | J10: C02, M04, M18, M21 | L10: C02, M04, M18, M21 | M10: Must | N10: 1 - Foundation and Configuration | O10: =IF(AND(G10>0,H10>0),"Covered","Gap") -> Covered
A11: 1 | B11: 1. General | C11: F04 | D11: Configure CoA mapping and accounting rules | E11: Masters / source references: M07, M12, M23, M32-M33; C05. These functions are reused from each applicable instrument. Project/Program IDs and source-owned details come from the existing Project/Program list. CoA/HoA and accounting entries use the existing chart and common accounting service. | F11: 1.5.4 | G11: =COUNTIF(Backlog!$C$5:$C$684,C11) -> 8 | H11: =COUNTIF(Tasks!$C$5:$C$3104,C11) -> 36 | I11: 36 | J11: C05, M07, M12, M23, M32, M33 | L11: C05, M07, M12, M23, M32, M33 | M11: Must | N11: 1 - Foundation and Configuration | O11: =IF(AND(G11>0,H11>0),"Covered","Gap") -> Covered
A12: 6 | B12: 6. Accounting by instrument type | C12: AC01 | D12: Accounting masters and configuration | E12: Register behavior: R01-R06 are current-position views backed by transaction history; R07-R19 retain event rows and balances; R20 is append-only audit history. Approved corrections add linked records or versions. Deactivation or closure must not delete financial history. | F12: 6.1.1 | G12: =COUNTIF(Backlog!$C$5:$C$684,C12) -> 8 | H12: =COUNTIF(Tasks!$C$5:$C$3104,C12) -> 36 | I12: 36 | J12: C05, C06 | K12: R01, R06, R07, R18, R19, R20 | L12: C05, C06, R01, R06, R07, R18, R19, R20 | M12: Must | N12: 1 - Foundation and Configuration | O12: =IF(AND(G12>0,H12>0),"Covered","Gap") -> Covered
A13: 6 | B13: 6. Accounting by instrument type | C13: AC02 | D13: First-time opening balances and migrated instruments | E13: Implement the controlled First-time opening balances and migrated instruments capability described in the source document. | F13: 6.1.5 | G13: =COUNTIF(Backlog!$C$5:$C$684,C13) -> 8 | H13: =COUNTIF(Tasks!$C$5:$C$3104,C13) -> 36 | J13: C05 | K13: R01, R17, R18, R20 | L13: C05, R01, R17, R18, R20 | M13: Must | N13: 1 - Foundation and Configuration | O13: =IF(AND(G13>0,H13>0),"Covered","Gap") -> Covered
A14: 1 | B14: 1. General | C14: F06 | D14: Maintain supporting documents | E14: Masters / source references: M31; approved or draft instrument/request reference. | F14: 1.6.1 | G14: =COUNTIF(Backlog!$C$5:$C$684,C14) -> 8 | H14: =COUNTIF(Tasks!$C$5:$C$3104,C14) -> 36 | J14: M31 | L14: M31 | M14: Must | N14: 2 - Core Debt Recording and Servicing | O14: =IF(AND(G14>0,H14>0),"Covered","Gap") -> Covered
A15: 1 | B15: 1. General | C15: F07 | D15: Link an existing Project or Program | E15: Masters / source references: M01, M04-M07, M11; C04, C06. | F15: 1.6.2 | G15: =COUNTIF(Backlog!$C$5:$C$684,C15) -> 8 | H15: =COUNTIF(Tasks!$C$5:$C$3104,C15) -> 36 | I15: 32, 34 | J15: C04, C06, M01, M04, M07, M11 | L15: C04, C06, M01, M04, M07, M11 | M15: Must | N15: 2 - Core Debt Recording and Servicing | O15: =IF(AND(G15>0,H15>0),"Covered","Gap") -> Covered
A16: 1 | B16: 1. General | C16: F25 | D16: Post debt accounting and reconcile | E16: Masters / source references: M04, M07, M09, M23, M32-M33; C05; source events and common GL. Apply each function only to the relevant instrument event. Loans use drawdowns, repayments or recoveries. Securities use evidenced issue/settlement and coupon/redemption events. Grants use receipts, transfers, utilisation and contractual refunds, not ordinary loan-principal/interest schedules. Guarantees use borrower monitoring, fees and an approved invocation obligation; they are not direct borrowing merely because they are recorded. | F16: 1.6.4 | G16: =COUNTIF(Backlog!$C$5:$C$684,C16) -> 8 | H16: =COUNTIF(Tasks!$C$5:$C$3104,C16) -> 36 | I16: 9, 20, 36 | J16: C05, M04, M07, M09, M23, M32, M33 | L16: C05, M04, M07, M09, M23, M32, M33 | M16: Must | N16: 2 - Core Debt Recording and Servicing | O16: =IF(AND(G16>0,H16>0),"Covered","Gap") -> Covered
A17: 1 | B17: 1. General | C17: F16 | D17: Prepare disbursement forecasts | E17: Masters / source references: M01-M06, M09, M25; approved instrument; C04. | F17: 1.7.1 | G17: =COUNTIF(Backlog!$C$5:$C$684,C17) -> 8 | H17: =COUNTIF(Tasks!$C$5:$C$3104,C17) -> 36 | I17: 19, 22 | J17: C04, M01, M06, M09, M25 | L17: C04, M01, M06, M09, M25 | M17: Must | N17: 2 - Core Debt Recording and Servicing | O17: =IF(AND(G17>0,H17>0),"Covered","Gap") -> Covered
A18: 1 | B18: 1. General | C18: F17 | D18: Record actual disbursements and funding receipts | E18: Masters / source references: M01-M09, M25, M31; instrument/allocation; C02, C04, C06. | F18: 1.7.2 | G18: =COUNTIF(Backlog!$C$5:$C$684,C18) -> 8 | H18: =COUNTIF(Tasks!$C$5:$C$3104,C18) -> 36 | I18: 21, 33 | J18: C02, C04, C06, M01, M09, M25, M31 | L18: C02, C04, C06, M01, M09, M25, M31 | M18: Must | N18: 2 - Core Debt Recording and Servicing | O18: =IF(AND(G18>0,H18>0),"Covered","Gap") -> Covered
A19: 1 | B19: 1. General | C19: F18 | D19: Generate debt-service schedules | E19: Masters / source references: M04, M09, M17-M24; approved terms/drawdowns; C02-C03. | F19: 1.7.3 | G19: =COUNTIF(Backlog!$C$5:$C$684,C19) -> 8 | H19: =COUNTIF(Tasks!$C$5:$C$3104,C19) -> 36 | I19: 2, 19, 22, 35 | J19: C02, C03, M04, M09, M17, M24 | L19: C02, C03, M04, M09, M17, M24 | M19: Must | N19: 2 - Core Debt Recording and Servicing | O19: =IF(AND(G19>0,H19>0),"Covered","Gap") -> Covered
A20: 1 | B20: 1. General | C20: F19 | D20: Create repayment Claim Requests and record settlement | E20: Masters / source references: M02, M04, M06-M09, M23, M31; schedule; existing claim/treasury services. | F20: 1.7.4 | G20: =COUNTIF(Backlog!$C$5:$C$684,C20) -> 8 | H20: =COUNTIF(Tasks!$C$5:$C$3104,C20) -> 36 | I20: 9, 20, 21 | J20: M02, M04, M06, M09, M23, M31 | L20: M02, M04, M06, M09, M23, M31 | M20: Must | N20: 2 - Core Debt Recording and Servicing | O20: =IF(AND(G20>0,H20>0),"Covered","Gap") -> Covered
A21: 1 | B21: 1. General | C21: F21 | D21: Manage arrears, penalties and waivers | E21: Masters / source references: M02, M04, M09, M23-M24, M31; schedule and actuals; C03. | F21: 1.7.5 | G21: =COUNTIF(Backlog!$C$5:$C$684,C21) -> 8 | H21: =COUNTIF(Tasks!$C$5:$C$3104,C21) -> 36 | J21: C03, M02, M04, M09, M23, M24, M31 | L21: C03, M02, M04, M09, M23, M24, M31 | M21: Must | N21: 2 - Core Debt Recording and Servicing | O21: =IF(AND(G21>0,H21>0),"Covered","Gap") -> Covered
A22: 1 | B22: 1. General | C22: F30 | D22: Close, cancel or reopen an instrument | E22: Masters / source references: M09, M31; instrument, schedules, balances and linked transactions. Shared outputs should support instrument-type and subtype filters, single instruments and the full portfolio. Show direct debt, government lending, grants and contingent guarantees separately before presenting any explicitly defined aggregation. | F22: 1.7.6 | G22: =COUNTIF(Backlog!$C$5:$C$684,C22) -> 8 | H22: =COUNTIF(Tasks!$C$5:$C$3104,C22) -> 36 | J22: M09, M31 | L22: M09, M31 | M22: Must | N22: 2 - Core Debt Recording and Servicing | O22: =IF(AND(G22>0,H22>0),"Covered","Gap") -> Covered
A23: 1 | B23: 1. General | C23: F27 | D23: Generate standard and international reports | E23: Masters / source references: M03-M04, M09, M12-M16, M34; C07. | F23: 1.8.2 | G23: =COUNTIF(Backlog!$C$5:$C$684,C23) -> 8 | H23: =COUNTIF(Tasks!$C$5:$C$3104,C23) -> 36 | I23: 37, 38, 39, 40, 41, 42, 43 | J23: C07, M03, M04, M09, M12, M16, M34 | L23: C07, M03, M04, M09, M12, M16, M34 | M23: Must | N23: 2 - Core Debt Recording and Servicing | O23: =IF(AND(G23>0,H23>0),"Covered","Gap") -> Covered
A24: 1 | B24: 1. General | C24: F29 | D24: Configure dashboards, alerts and escalation | E24: Masters / source references: M01, M04, M09-M10, M35; C08. | F24: 1.8.4 | G24: =COUNTIF(Backlog!$C$5:$C$684,C24) -> 8 | H24: =COUNTIF(Tasks!$C$5:$C$3104,C24) -> 36 | I24: 37, 38, 39, 40, 41, 42, 43 | J24: C08, M01, M04, M09, M10, M35 | L24: C08, M01, M04, M09, M10, M35 | M24: Must | N24: 2 - Core Debt Recording and Servicing | O24: =IF(AND(G24>0,H24>0),"Covered","Gap") -> Covered
A25: 2 | B25: 2. Loans | C25: F05-D | D25: Domestic loans | E25: Masters / source references: M01-M07, M12-M14, M17-M25, M31; C03-C05. | F25: 2.1 | G25: =COUNTIF(Backlog!$C$5:$C$684,C25) -> 8 | H25: =COUNTIF(Tasks!$C$5:$C$3104,C25) -> 36 | I25: 1, 2 | J25: C03, C05, M01, M07, M12, M14, M17, M25, M31 | L25: C03, C05, M01, M07, M12, M14, M17, M25, M31 | M25: Must | N25: 2 - Core Debt Recording and Servicing | O25: =IF(AND(G25>0,H25>0),"Covered","Gap") -> Covered
A26: 2 | B26: 2. Loans | C26: F05-E | D26: External loans | E26: Masters / source references: M01-M07, M12-M14, M17-M25, M31; C03-C05. These are M14 arrangements, not substitutes for the Domestic/External classification. Retain links to the source instrument and its classification, while maintaining each subsidiary agreement and borrower-recovery obligation separately. | F26: 2.2 | G26: =COUNTIF(Backlog!$C$5:$C$684,C26) -> 8 | H26: =COUNTIF(Tasks!$C$5:$C$3104,C26) -> 36 | I26: 1, 2 | J26: C03, C05, M01, M07, M12, M14, M17, M25, M31 | L26: C03, C05, M01, M07, M12, M14, M17, M25, M31 | M26: Must | N26: 2 - Core Debt Recording and Servicing | O26: =IF(AND(G26>0,H26>0),"Covered","Gap") -> Covered
A27: 2 | B27: 2. Loans | C27: F20 | D27: Borrower recoveries | E27: Masters / source references: M02, M04, M07-M09, M23, M31; subsidiary/government loan; C06. | F27: 2.4 | G27: =COUNTIF(Backlog!$C$5:$C$684,C27) -> 8 | H27: =COUNTIF(Tasks!$C$5:$C$3104,C27) -> 36 | I27: 9, 21 | J27: C06, M02, M04, M07, M09, M23, M31 | L27: C06, M02, M04, M07, M09, M23, M31 | M27: Must | N27: 2 - Core Debt Recording and Servicing | O27: =IF(AND(G27>0,H27>0),"Covered","Gap") -> Covered
A28: 6 | B28: 6. Accounting by instrument type | C28: AC03 | D28: Domestic loan accounting | E28: Source functions / masters: F05-D, F17-F19, F21-F22, F25; M07, M13, M23, M32-M33; C02-C05 | F28: 6.2.1 | G28: =COUNTIF(Backlog!$C$5:$C$684,C28) -> 8 | H28: =COUNTIF(Tasks!$C$5:$C$3104,C28) -> 36 | I28: 1, 2, 9, 20, 21, 33 | J28: C02, C05, M07, M13, M23, M32, M33 | K28: R01, R06, R07, R10, R12, R14, R17, R18, R20 | L28: C02, C05, M07, M13, M23, M32, M33, R01, R06, R07, R10, R12, R14, R17, R18, R20 | M28: Must | N28: 2 - Core Debt Recording and Servicing | O28: =IF(AND(G28>0,H28>0),"Covered","Gap") -> Covered
A29: 6 | B29: 6. Accounting by instrument type | C29: AC04 | D29: External loan accounting | E29: Source functions / masters: F05-E, F17-F19, F22, F25; M03-M04, M07, M25; C02, C05-C06 | F29: 6.2.2 | G29: =COUNTIF(Backlog!$C$5:$C$684,C29) -> 8 | H29: =COUNTIF(Tasks!$C$5:$C$3104,C29) -> 36 | I29: 1, 2, 9, 20, 21, 33 | J29: C02, C05, C06, M03, M04, M07, M25 | K29: R01, R06, R10, R12, R14, R17, R18, R20 | L29: C02, C05, C06, M03, M04, M07, M25, R01, R06, R10, R12, R14, R17, R18, R20 | M29: Must | N29: 2 - Core Debt Recording and Servicing | O29: =IF(AND(G29>0,H29>0),"Covered","Gap") -> Covered
A30: 6 | B30: 6. Accounting by instrument type | C30: AC22 | D30: Cross-instrument adjustments, reconciliation and close | E30: IPSAS 41 addresses classification and measurement of financial instruments and includes public-sector guidance for concessionary loans and financial guarantees. Use it only if adopted by the applicable authority. IPSASB - IPSAS 41, Financial Instruments IPSASB - Public-sector financial instruments guidance IPSAS 47 distinguishes revenue accounting models according to whether a binding arrangement exists. IPSAS 48 provides guidance for transfer expenses. These references explain why the grant and on-granting rules require explicit policy configuration. IPSASB - IPSAS 47, Revenue IPSASB - IPSAS 48, Transfer Expenses For comparison, New Zealand PBE IPSAS 41, paragraphs 45(c) and AG131-AG132, explicitly addresses financial-guarantee recognition and measurement. It supports the design distinction between guarantee exposure and a recognised guarantee liability; it is not assumed to govern this implementation. XRB - PBE IPSAS 41, Financial Instruments | F30: 6.6 | G30: =COUNTIF(Backlog!$C$5:$C$684,C30) -> 8 | H30: =COUNTIF(Tasks!$C$5:$C$3104,C30) -> 36 | I30: 35 | K30: R01, R20 | L30: R01, R20 | M30: Must | N30: 2 - Core Debt Recording and Servicing | O30: =IF(AND(G30>0,H30>0),"Covered","Gap") -> Covered
A31: 1 | B31: 1. General | C31: F24 | D31: Monitor Project/Program expenditure and utilisation | E31: Masters / source references: M01, M05-M07, M11, M25; C04, C06; owning project/financial systems. | F31: 1.6.3 | G31: =COUNTIF(Backlog!$C$5:$C$684,C31) -> 8 | H31: =COUNTIF(Tasks!$C$5:$C$3104,C31) -> 36 | I31: 32, 33, 34, 36 | J31: C04, C06, M01, M05, M07, M11, M25 | L31: C04, C06, M01, M05, M07, M11, M25 | M31: Should | N31: 3 - Extended Instruments and Accounting | O31: =IF(AND(G31>0,H31>0),"Covered","Gap") -> Covered
A32: 2 | B32: 2. Loans | C32: F08 | D32: Record back-to-back lending | E32: Masters / source references: M01-M07, M14, M17-M24, M31; parent loan; C03-C04. | F32: 2.3.1 | G32: =COUNTIF(Backlog!$C$5:$C$684,C32) -> 8 | H32: =COUNTIF(Tasks!$C$5:$C$3104,C32) -> 36 | I32: 3 | J32: C03, C04, M01, M07, M14, M17, M24, M31 | L32: C03, C04, M01, M07, M14, M17, M24, M31 | M32: Should | N32: 3 - Extended Instruments and Accounting | O32: =IF(AND(G32>0,H32>0),"Covered","Gap") -> Covered
A33: 2 | B33: 2. Loans | C33: F09 | D33: Split a loan among sub-borrowers | E33: Masters / source references: M01-M07, M14, M17-M24, M31; parent loan; C03-C04. | F33: 2.3.2 | G33: =COUNTIF(Backlog!$C$5:$C$684,C33) -> 8 | H33: =COUNTIF(Tasks!$C$5:$C$3104,C33) -> 36 | I33: 4 | J33: C03, C04, M01, M07, M14, M17, M24, M31 | L33: C03, C04, M01, M07, M14, M17, M24, M31 | M33: Should | N33: 3 - Extended Instruments and Accounting | O33: =IF(AND(G33>0,H33>0),"Covered","Gap") -> Covered
A34: 2 | B34: 2. Loans | C34: F10 | D34: Create and maintain a loan pool | E34: Masters / source references: M01-M07, M14, M31; source instruments; C04. | F34: 2.3.3 | G34: =COUNTIF(Backlog!$C$5:$C$684,C34) -> 8 | H34: =COUNTIF(Tasks!$C$5:$C$3104,C34) -> 36 | I34: 5 | J34: C04, M01, M07, M14, M31 | L34: C04, M01, M07, M14, M31 | M34: Should | N34: 3 - Extended Instruments and Accounting | O34: =IF(AND(G34>0,H34>0),"Covered","Gap") -> Covered
A35: 2 | B35: 2. Loans | C35: F14 | D35: Record government loans from budget | E35: Masters / source references: M01-M09, M14, M17-M24, M31; existing budget allocation. | F35: 2.3.4 | G35: =COUNTIF(Backlog!$C$5:$C$684,C35) -> 8 | H35: =COUNTIF(Tasks!$C$5:$C$3104,C35) -> 36 | I35: 8 | J35: M01, M09, M14, M17, M24, M31 | L35: M01, M09, M14, M17, M24, M31 | M35: Should | N35: 3 - Extended Instruments and Accounting | O35: =IF(AND(G35>0,H35>0),"Covered","Gap") -> Covered
A36: 2 | B36: 2. Loans | C36: F22 | D36: Loan restructuring | E36: Masters / source references: M04, M09, M23, M28-M29, M31; loan terms and balances. | F36: 2.5 | G36: =COUNTIF(Backlog!$C$5:$C$684,C36) -> 8 | H36: =COUNTIF(Tasks!$C$5:$C$3104,C36) -> 36 | I36: 23, 24, 25, 26 | J36: M04, M09, M23, M28, M29, M31 | L36: M04, M09, M23, M28, M29, M31 | M36: Should | N36: 3 - Extended Instruments and Accounting | O36: =IF(AND(G36>0,H36>0),"Covered","Gap") -> Covered
A37: 3 | B37: 3. Debt securities | C37: F15-TB | D37: Treasury bills | E37: Masters / source references: M01-M04, M07-M09, M12-M13, M15-M19, M23, M31. | F37: 3.1 | G37: =COUNTIF(Backlog!$C$5:$C$684,C37) -> 8 | H37: =COUNTIF(Tasks!$C$5:$C$3104,C37) -> 36 | I37: 10, 11, 12, 17 | J37: M01, M04, M07, M09, M12, M13, M15, M19, M23, M31 | L37: M01, M04, M07, M09, M12, M13, M15, M19, M23, M31 | M37: Should | N37: 3 - Extended Instruments and Accounting | O37: =IF(AND(G37>0,H37>0),"Covered","Gap") -> Covered
A38: 3 | B38: 3. Debt securities | C38: F15-BD | D38: Bonds | E38: Masters / source references: M01-M04, M07-M09, M12-M13, M15-M19, M23, M31. | F38: 3.2 | G38: =COUNTIF(Backlog!$C$5:$C$684,C38) -> 8 | H38: =COUNTIF(Tasks!$C$5:$C$3104,C38) -> 36 | I38: 10, 11, 13, 17 | J38: M01, M04, M07, M09, M12, M13, M15, M19, M23, M31 | L38: M01, M04, M07, M09, M12, M13, M15, M19, M23, M31 | M38: Should | N38: 3 - Extended Instruments and Accounting | O38: =IF(AND(G38>0,H38>0),"Covered","Gap") -> Covered
A39: 3 | B39: 3. Debt securities | C39: F15-TR | D39: Tax/Reserve certificates | E39: Masters / source references: M01-M04, M07-M09, M12-M13, M15-M19, M23, M31. | F39: 3.3 | G39: =COUNTIF(Backlog!$C$5:$C$684,C39) -> 8 | H39: =COUNTIF(Tasks!$C$5:$C$3104,C39) -> 36 | I39: 10, 11, 14, 17 | J39: M01, M04, M07, M09, M12, M13, M15, M19, M23, M31 | L39: M01, M04, M07, M09, M12, M13, M15, M19, M23, M31 | M39: Should | N39: 3 - Extended Instruments and Accounting | O39: =IF(AND(G39>0,H39>0),"Covered","Gap") -> Covered
A40: 3 | B40: 3. Debt securities | C40: F15-PN | D40: Promissory notes | E40: Masters / source references: M01-M04, M07-M09, M12-M13, M15-M19, M23, M31. | F40: 3.4 | G40: =COUNTIF(Backlog!$C$5:$C$684,C40) -> 8 | H40: =COUNTIF(Tasks!$C$5:$C$3104,C40) -> 36 | I40: 10, 11, 15, 17 | J40: M01, M04, M07, M09, M12, M13, M15, M19, M23, M31 | L40: M01, M04, M07, M09, M12, M13, M15, M19, M23, M31 | M40: Should | N40: 3 - Extended Instruments and Accounting | O40: =IF(AND(G40>0,H40>0),"Covered","Gap") -> Covered
A41: 3 | B41: 3. Debt securities | C41: F15-CP | D41: Commercial paper | E41: Masters / source references: M01-M04, M07-M09, M12-M13, M15-M19, M23, M31. | F41: 3.5 | G41: =COUNTIF(Backlog!$C$5:$C$684,C41) -> 8 | H41: =COUNTIF(Tasks!$C$5:$C$3104,C41) -> 36 | I41: 10, 11, 16, 17 | J41: M01, M04, M07, M09, M12, M13, M15, M19, M23, M31 | L41: M01, M04, M07, M09, M12, M13, M15, M19, M23, M31 | M41: Should | N41: 3 - Extended Instruments and Accounting | O41: =IF(AND(G41>0,H41>0),"Covered","Gap") -> Covered
A42: 3 | B42: 3. Debt securities | C42: F23 | D42: Security restructuring | E42: Masters / source references: M04, M09, M15, M30-M31; security issues and balances. | F42: 3.6 | G42: =COUNTIF(Backlog!$C$5:$C$684,C42) -> 8 | H42: =COUNTIF(Tasks!$C$5:$C$3104,C42) -> 36 | I42: 27, 28, 29, 30, 31 | J42: M04, M09, M15, M30, M31 | L42: M04, M09, M15, M30, M31 | M42: Should | N42: 3 - Extended Instruments and Accounting | O42: =IF(AND(G42>0,H42>0),"Covered","Gap") -> Covered
... A49: 5 | B49: 5. Guarantees | C49: F13-E | D49: Guaranteed external loans | E49: Masters / source references: M01-M04, M08, M12-M13, M23, M27, M31; underlying loan. | F49: 5.2 | G49: =COUNTIF(Backlog!$C$5:$C$684,C49) -> 8 | H49: =COUNTIF(Tasks!$C$5:$C$3104,C49) -> 36 | I49: 7 | J49: M01, M04, M08, M12, M13, M23, M27, M31 | L49: M01, M04, M08, M12, M13, M23, M27, M31 | M49: Should | N49: 3 - Extended Instruments and Accounting | O49: =IF(AND(G49>0,H49>0),"Covered","Gap") -> Covered
A50: 6 | B50: 6. Accounting by instrument type | C50: AC05 | D50: Back-to-back lending accounting | E50: Source functions / masters: F08, F17-F20, F25; M14, M23; C04-C06 | F50: 6.2.3 | G50: =COUNTIF(Backlog!$C$5:$C$684,C50) -> 8 | H50: =COUNTIF(Tasks!$C$5:$C$3104,C50) -> 36 | I50: 3, 21 | J50: C04, C05, C06, M14, M23 | K50: R01, R02, R06, R12, R17, R18, R20 | L50: C04, C05, C06, M14, M23, R01, R02, R06, R12, R17, R18, R20 | M50: Should | N50: 3 - Extended Instruments and Accounting | O50: =IF(AND(G50>0,H50>0),"Covered","Gap") -> Covered
A51: 6 | B51: 6. Accounting by instrument type | C51: AC06 | D51: Split subsidiary loan accounting | E51: Source functions / masters: F09, F17-F20, F25; M14; C04-C06 | F51: 6.2.4 | G51: =COUNTIF(Backlog!$C$5:$C$684,C51) -> 8 | H51: =COUNTIF(Tasks!$C$5:$C$3104,C51) -> 36 | I51: 4, 21 | J51: C04, C05, C06, M14 | K51: R01, R02, R06, R12, R17, R18, R20 | L51: C04, C05, C06, M14, R01, R02, R06, R12, R17, R18, R20 | M51: Should | N51: 3 - Extended Instruments and Accounting | O51: =IF(AND(G51>0,H51>0),"Covered","Gap") -> Covered
A52: 6 | B52: 6. Accounting by instrument type | C52: AC07 | D52: Pooled loan accounting | E52: Source functions / masters: F10, F17-F20, F25; M14; C04-C06 | F52: 6.2.5 | G52: =COUNTIF(Backlog!$C$5:$C$684,C52) -> 8 | H52: =COUNTIF(Tasks!$C$5:$C$3104,C52) -> 36 | I52: 5, 21 | J52: C04, C05, C06, M14 | K52: R01, R02, R06, R12, R17, R18, R20 | L52: C04, C05, C06, M14, R01, R02, R06, R12, R17, R18, R20 | M52: Should | N52: 3 - Extended Instruments and Accounting | O52: =IF(AND(G52>0,H52>0),"Covered","Gap") -> Covered
A53: 6 | B53: 6. Accounting by instrument type | C53: AC08 | D53: Government loans from budgetary resources | E53: Source functions / masters: F14, F17-F20, F25; M06, M14; C04-C06 | F53: 6.2.6 | G53: =COUNTIF(Backlog!$C$5:$C$684,C53) -> 8 | H53: =COUNTIF(Tasks!$C$5:$C$3104,C53) -> 36 | I53: 8, 9, 21 | J53: C04, C05, C06, M06, M14 | K53: R02, R06, R09, R11, R14, R17, R18, R20 | L53: C04, C05, C06, M06, M14, R02, R06, R09, R11, R14, R17, R18, R20 | M53: Should | N53: 3 - Extended Instruments and Accounting | O53: =IF(AND(G53>0,H53>0),"Covered","Gap") -> Covered
A54: 6 | B54: 6. Accounting by instrument type | C54: AC09 | D54: Loan restructuring and relief accounting | E54: Source functions / masters: F22, F25; M28-M29; C05 | F54: 6.2.7 | G54: =COUNTIF(Backlog!$C$5:$C$684,C54) -> 8 | H54: =COUNTIF(Tasks!$C$5:$C$3104,C54) -> 36 | I54: 23, 24, 25, 26 | J54: C05, M28, M29 | K54: R01, R02, R07, R14, R18, R20 | L54: C05, M28, M29, R01, R02, R07, R14, R18, R20 | M54: Should | N54: 3 - Extended Instruments and Accounting | O54: =IF(AND(G54>0,H54>0),"Covered","Gap") -> Covered
A55: 6 | B55: 6. Accounting by instrument type | C55: AC10 | D55: Treasury bill accounting | E55: Source functions / masters: F15-TB, F18-F19, F23, F25; M15-M16; C03, C05 | F55: 6.3.1 | G55: =COUNTIF(Backlog!$C$5:$C$684,C55) -> 8 | H55: =COUNTIF(Tasks!$C$5:$C$3104,C55) -> 36 | I55: 10, 11, 12, 17, 20 | J55: C03, C05, M15, M16 | K55: R03, R07, R10, R14, R18, R20 | L55: C03, C05, M15, M16, R03, R07, R10, R14, R18, R20 | M55: Should | N55: 3 - Extended Instruments and Accounting | O55: =IF(AND(G55>0,H55>0),"Covered","Gap") -> Covered
A56: 6 | B56: 6. Accounting by instrument type | C56: AC11 | D56: Bond accounting | E56: Source functions / masters: F15-BD, F18-F19, F23, F25; M15, M17-M24; C03, C05 | F56: 6.3.2 | G56: =COUNTIF(Backlog!$C$5:$C$684,C56) -> 8 | H56: =COUNTIF(Tasks!$C$5:$C$3104,C56) -> 36 | I56: 10, 11, 13, 17, 20 | J56: C03, C05, M15, M17, M24 | K56: R03, R07, R10, R12, R14, R18, R20 | L56: C03, C05, M15, M17, M24, R03, R07, R10, R12, R14, R18, R20 | M56: Should | N56: 3 - Extended Instruments and Accounting | O56: =IF(AND(G56>0,H56>0),"Covered","Gap") -> Covered
A57: 6 | B57: 6. Accounting by instrument type | C57: AC12 | D57: Tax/Reserve certificate accounting | E57: Source functions / masters: F15-TR, F18-F19, F25; M15; C05-C06 | F57: 6.3.3 | G57: =COUNTIF(Backlog!$C$5:$C$684,C57) -> 8 | H57: =COUNTIF(Tasks!$C$5:$C$3104,C57) -> 36 | I57: 10, 11, 14, 17, 20 | J57: C05, C06, M15 | K57: R03, R07, R10, R18, R20 | L57: C05, C06, M15, R03, R07, R10, R18, R20 | M57: Should | N57: 3 - Extended Instruments and Accounting | O57: =IF(AND(G57>0,H57>0),"Covered","Gap") -> Covered
A58: 6 | B58: 6. Accounting by instrument type | C58: AC13 | D58: Promissory note accounting | E58: Source functions / masters: F15-PN, F18-F19, F25; M15; C05-C06 | F58: 6.3.4 | G58: =COUNTIF(Backlog!$C$5:$C$684,C58) -> 8 | H58: =COUNTIF(Tasks!$C$5:$C$3104,C58) -> 36 | I58: 10, 11, 15, 17, 20 | J58: C05, C06, M15 | K58: R03, R07, R10, R14, R18, R20 | L58: C05, C06, M15, R03, R07, R10, R14, R18, R20 | M58: Should | N58: 3 - Extended Instruments and Accounting | O58: =IF(AND(G58>0,H58>0),"Covered","Gap") -> Covered
A59: 6 | B59: 6. Accounting by instrument type | C59: AC14 | D59: Commercial paper accounting | E59: Source functions / masters: F15-CP, F18-F19, F25; M15; C03, C05 | F59: 6.3.5 | G59: =COUNTIF(Backlog!$C$5:$C$684,C59) -> 8 | H59: =COUNTIF(Tasks!$C$5:$C$3104,C59) -> 36 | I59: 10, 11, 16, 17, 20 | J59: C03, C05, M15 | K59: R03, R07, R10, R14, R18, R20 | L59: C03, C05, M15, R03, R07, R10, R14, R18, R20 | M59: Should | N59: 3 - Extended Instruments and Accounting | O59: =IF(AND(G59>0,H59>0),"Covered","Gap") -> Covered
A60: 6 | B60: 6. Accounting by instrument type | C60: AC15 | D60: Security restructuring accounting | E60: Source functions / masters: F23, F25; M30; C05 | F60: 6.3.6 | G60: =COUNTIF(Backlog!$C$5:$C$684,C60) -> 8 | H60: =COUNTIF(Tasks!$C$5:$C$3104,C60) -> 36 | I60: 27, 28, 29, 30, 31 | J60: C05, M30 | K60: R03, R07, R10, R14, R18, R20 | L60: C05, M30, R03, R07, R10, R14, R18, R20 | M60: Should | N60: 3 - Extended Instruments and Accounting | O60: =IF(AND(G60>0,H60>0),"Covered","Gap") -> Covered
A61: 6 | B61: 6. Accounting by instrument type | C61: AC16 | D61: Project grant accounting | E61: Source functions / masters: F11-PR, F17, F24-F25; M05, M25-M26; C04-C06 | F61: 6.4.1 | G61: =COUNTIF(Backlog!$C$5:$C$684,C61) -> 8 | H61: =COUNTIF(Tasks!$C$5:$C$3104,C61) -> 36 | I61: 18, 33 | J61: C04, C05, C06, M05, M25, M26 | K61: R04, R06, R07, R10, R15, R17, R18, R20 | L61: C04, C05, C06, M05, M25, M26, R04, R06, R07, R10, R15, R17, R18, R20 | M61: Should | N61: 3 - Extended Instruments and Accounting | O61: =IF(AND(G61>0,H61>0),"Covered","Gap") -> Covered
... A77: 12 | B77: 12. Additional accounting by loan/facility type | C77: AC24-S | D77: Central-government loans to States/UTs | E77: Implement the controlled Central-government loans to States/UTs capability described in the source document. | F77: 12.2 | G77: =COUNTIF(Backlog!$C$5:$C$684,C77) -> 8 | H77: =COUNTIF(Tasks!$C$5:$C$3104,C77) -> 36 | I77: 3, 4, 5, 8, 9, 20, 21 | J77: C05 | K77: R02, R06, R09, R11, R13, R17, R18, R19, R20, R21 | L77: C05, R02, R06, R09, R11, R13, R17, R18, R19, R20, R21 | M77: Should | N77: 4 - Advanced Lending and Central-bank Facilities | O77: =IF(AND(G77>0,H77>0),"Covered","Gap") -> Covered
A78: 12 | B78: 12. Additional accounting by loan/facility type | C78: AC24-B | D78: Central-government loans to other bodies | E78: Implement the controlled Central-government loans to other bodies capability described in the source document. | F78: 12.3 | G78: =COUNTIF(Backlog!$C$5:$C$684,C78) -> 8 | H78: =COUNTIF(Tasks!$C$5:$C$3104,C78) -> 36 | J78: C05 | K78: R02, R06, R09, R11, R13, R17, R18, R19, R20, R21 | L78: C05, R02, R06, R09, R11, R13, R17, R18, R19, R20, R21 | M78: Should | N78: 4 - Advanced Lending and Central-bank Facilities | O78: =IF(AND(G78>0,H78>0),"Covered","Gap") -> Covered
A79: 12 | B79: 12. Additional accounting by loan/facility type | C79: AC25 | D79: WMA and secured/Special Drawing Facility accounting | E79: Implement the controlled WMA and secured/Special Drawing Facility accounting capability described in the source document. | F79: 12.4 | G79: =COUNTIF(Backlog!$C$5:$C$684,C79) -> 8 | H79: =COUNTIF(Tasks!$C$5:$C$3104,C79) -> 36 | I79: 1, 2, 9, 19, 20, 21, 22 | J79: C05 | K79: R01, R07, R10, R18, R19, R20, R24 | L79: C05, R01, R07, R10, R18, R19, R20, R24 | M79: Should | N79: 4 - Advanced Lending and Central-bank Facilities | O79: =IF(AND(G79>0,H79>0),"Covered","Gap") -> Covered
A80: 12 | B80: 12. Additional accounting by loan/facility type | C80: AC26 | D80: Central-bank overdraft accounting | E80: Implement the controlled Central-bank overdraft accounting capability described in the source document. | F80: 12.5 | G80: =COUNTIF(Backlog!$C$5:$C$684,C80) -> 8 | H80: =COUNTIF(Tasks!$C$5:$C$3104,C80) -> 36 | I80: 1, 2, 9, 19, 20, 21, 22 | J80: C05 | K80: R01, R07, R08, R10, R18, R19, R20, R24 | L80: C05, R01, R07, R08, R10, R18, R19, R20, R24 | M80: Should | N80: 4 - Advanced Lending and Central-bank Facilities | O80: =IF(AND(G80>0,H80>0),"Covered","Gap") -> Covered
A81: 1 | B81: 1. General | C81: F26 | D81: Forecast debt stock and cash flows | E81: Masters / source references: M04, M09, M12-M24; approved actuals, terms and forecast versions. | F81: 1.8.1 | G81: =COUNTIF(Backlog!$C$5:$C$684,C81) -> 8 | H81: =COUNTIF(Tasks!$C$5:$C$3104,C81) -> 36 | I81: 19, 22, 39, 40 | J81: M04, M09, M12, M24 | L81: M04, M09, M12, M24 | M81: Should | N81: 5 - Analytics and Country Configuration | O81: =IF(AND(G81>0,H81>0),"Covered","Gap") -> Covered
A82: 1 | B82: 1. General | C82: F28 | D82: Create country-specific report templates | E82: Masters / source references: M10, M34; C07; authorised debt/project/accounting data sources. | F82: 1.8.3 | G82: =COUNTIF(Backlog!$C$5:$C$684,C82) -> 8 | H82: =COUNTIF(Tasks!$C$5:$C$3104,C82) -> 36 | I82: 38, 41, 43 | J82: C07, M10, M34 | L82: C07, M10, M34 | M82: Should | N82: 5 - Analytics and Country Configuration | O82: =IF(AND(G82>0,H82>0),"Covered","Gap") -> Covered

Sheet Backlog
A1: User Story Backlog
A2: Every story is mapped to the source feature and includes function-specific Given-When-Then acceptance criteria.
A4: Epic Section | B4: Epic | C4: Feature ID | D4: Feature | E4: Story ID | F4: Actor | G4: Workflow | H4: User Story | I4: Acceptance Criteria (Given-When-Then) | J4: Source Requirement | K4: Master / Config Refs | L4: Register Refs | M4: FRS Sl. Nos. | N4: Dependencies | O4: Priority | P4: Suggested Phase | Q4: Source Section | R4: Backlog Status
A5: 0 | B5: Data Foundation and Traceability | C5: DF01 | D5: Master data and shared-source integration | E5: DF01-US01 | F5: Configuration Administrator | G5: Data foundation | H5: As a Configuration Administrator, I want to maintain or integrate M01 - Organisation / agency / existing organisation; organisation_hierarchy, so that approved debt functions use one controlled and traceable value source. | I5: AC1. Given M01 is implemented, when a value is created, fetched or synchronised, then the following ownership shall be enforced: Existing shared source. AC2. Given a record is entered or received, when it is validated, then every field, required/conditional flag, permitted value and validation documented for M01 in the Data Objects sheet shall be enforced. AC3. Given the object is source-owned, when Debt Management fetches or displays the record, then the original source ID shall be reused, source attributes shall remain read-only and no duplicate master shall be created. AC4. Given a debt-specific value is created or modified, when it is submitted for activation, then F01 Maker-Checker-Approver, effective dates, active/inactive status and immutable history shall apply before the value is used. AC5. Given an approved value becomes effective, when an applicable function loads its selectors or validations, then the value shall be available only in the applicable functions: Derived from Annexure B and referenced feature metadata. | J5: Effective-dated master/reference data; source-owned IDs are reused where identified. organisation_id (FK) | R | Existing ORG001; do not generate a second agency ID. organisation_type (FK) | R | Approved source value: Ministry, Treasury, Agency or Local Government. parent_organisation_id (FK) | C | Existing hierarchy parent; nullable at root or where source permits. hierarchy_level / path (source fields) | R | Source-defined levels, not a hard-coded government structure. country_id (FK M03) | R | Organisation country from source. validity / source_status (source fields) | R | Read-only eligibility for new requests. Create/modify through F01 under Maker-Checker-Approver; approved changes apply prospectively and preserve historical references. | K5: M01 | N5: F01-F04, AC01, C01, R19-R20 | O5: Must | P5: 1 - Foundation and Configuration | Q5: Section 8.3.1 | R5: Ready for Review
A6: 0 | B6: Data Foundation and Traceability | C6: DF01 | D6: Master data and shared-source integration | E6: DF01-US02 | F6: Configuration Administrator | G6: Data foundation | H6: As a Configuration Administrator, I want to maintain or integrate M02 - Counterparty and role / existing counterparty; counterparty_role, so that approved debt functions use one controlled and traceable value source. | I6: AC1. Given M02 is implemented, when a value is created, fetched or synchronised, then the following ownership shall be enforced: Existing shared source. AC2. Given a record is entered or received, when it is validated, then every field, required/conditional flag, permitted value and validation documented for M02 in the Data Objects sheet shall be enforced. AC3. Given the object is source-owned, when Debt Management fetches or displays the record, then the original source ID shall be reused, source attributes shall remain read-only and no duplicate master shall be created. AC4. Given a debt-specific value is created or modified, when it is submitted for activation, then F01 Maker-Checker-Approver, effective dates, active/inactive status and immutable history shall apply before the value is used. AC5. Given an approved value becomes effective, when an applicable function loads its selectors or validations, then the value shall be available only in the applicable functions: Derived from Annexure B and referenced feature metadata. | J6: Effective-dated master/reference data; source-owned IDs are reused where identified. counterparty_id / legal_name (FK / text) | R | CP001 / Example Development Bank; source-owned. resident_country_id (FK M03) | R | Country of residence used by approved classification rule. counterparty_category (source FK) | R | Government, Public corporation, Bank, Multilateral institution or other source category. role_id / counterparty_id (FK pair, child row) | R | One party may have several roles; avoid duplicate party records. organisation_id (FK M01) | C | Link if the party is also an existing government agency. contact_reference (source FK) | O | Existing approved address/contact record, not payment authority. Create/modify through F01 under Maker-Checker-Approver; approved changes apply prospectively and preserve historical references. | K6: M02 | N6: F01-F04, AC01, C01, R19-R20 | O6: Must | P6: 1 - Foundation and Configuration | Q6: Section 8.3.2 | R6: Ready for Review
A7: 0 | B7: Data Foundation and Traceability | C7: DF01 | D7: Master data and shared-source integration | E7: DF01-US03 | F7: Configuration Administrator | G7: Data foundation | H7: As a Configuration Administrator, I want to maintain or integrate M03 - Country / residency / existing country; residency_rule_reference, so that approved debt functions use one controlled and traceable value source. | I7: AC1. Given M03 is implemented, when a value is created, fetched or synchronised, then the following ownership shall be enforced: Existing shared source. AC2. Given a record is entered or received, when it is validated, then every field, required/conditional flag, permitted value and validation documented for M03 in the Data Objects sheet shall be enforced. AC3. Given the object is source-owned, when Debt Management fetches or displays the record, then the original source ID shall be reused, source attributes shall remain read-only and no duplicate master shall be created. AC4. Given a debt-specific value is created or modified, when it is submitted for activation, then F01 Maker-Checker-Approver, effective dates, active/inactive status and immutable history shall apply before the value is used. AC5. Given an approved value becomes effective, when an applicable function loads its selectors or validations, then the value shall be available only in the applicable functions: Derived from Annexure B and referenced feature metadata. | J7: Effective-dated master/reference data; source-owned IDs are reused where identified. country_code (text) | R | Approved country code, e.g., IN, NP, JP. country_name (text) | R | Source country label. reporting_country_id (FK) | R | Country of the reporting entity; drives resident/non-resident comparison. classification_rule_id (FK configuration) | R | Approved country-specific residency rule; no currency-only inference. Create/modify through F01 under Maker-Checker-Approver; approved changes apply prospectively and preserve historical references. | K7: M03 | N7: F01-F04, AC01, C01, R19-R20 | O7: Must | P7: 1 - Foundation and Configuration | Q7: Section 8.3.3 | R7: Ready for Review
A8: 0 | B8: Data Foundation and Traceability | C8: DF01 | D8: Master data and shared-source integration | E8: DF01-US04 | F8: Configuration Administrator | G8: Data foundation | H8: As a Configuration Administrator, I want to maintain or integrate M04 - Currency / existing currency, so that approved debt functions use one controlled and traceable value source. | I8: AC1. Given M04 is implemented, when a value is created, fetched or synchronised, then the following ownership shall be enforced: Existing shared source. AC2. Given a record is entered or received, when it is validated, then every field, required/conditional flag, permitted value and validation documented for M04 in the Data Objects sheet shall be enforced. AC3. Given the object is source-owned, when Debt Management fetches or displays the record, then the original source ID shall be reused, source attributes shall remain read-only and no duplicate master shall be created. AC4. Given a debt-specific value is created or modified, when it is submitted for activation, then F01 Maker-Checker-Approver, effective dates, active/inactive status and immutable history shall apply before the value is used. AC5. Given an approved value becomes effective, when an applicable function loads its selectors or validations, then the value shall be available only in the applicable functions: Derived from Annexure B and referenced feature metadata. | J8: Effective-dated master/reference data; source-owned IDs are reused where identified. currency_code (text) | R | USD, EUR, JPY or the configured local currency. currency_name (text) | R | Source display name. decimal_precision (integer) | R | Example USD=2; JPY=0, from approved source. rounding_rule_id (FK) | R | Approved rounding policy for currency amounts. reporting_entity_id / local_currency_id (FK pair, child row) | R | One reporting/base currency per entity and effective period. Create/modify through F01 under Maker-Checker-Approver; approved changes apply prospectively and preserve historical references. | K8: M04 | N8: F01-F04, AC01, C01, R19-R20 | O8: Must | P8: 1 - Foundation and Configuration | Q8: Section 8.3.4 | R8: Ready for Review
A9: 0 | B9: Data Foundation and Traceability | C9: DF01 | D9: Master data and shared-source integration | E9: DF01-US05 | F9: Configuration Administrator | G9: Data foundation | H9: As a Configuration Administrator, I want to maintain or integrate M05 - Project / Program / existing project_program; existing component, so that approved debt functions use one controlled and traceable value source. | I9: AC1. Given M05 is implemented, when a value is created, fetched or synchronised, then the following ownership shall be enforced: Existing shared source. AC2. Given a record is entered or received, when it is validated, then every field, required/conditional flag, permitted value and validation documented for M05 in the Data Objects sheet shall be enforced. AC3. Given the object is source-owned, when Debt Management fetches or displays the record, then the original source ID shall be reused, source attributes shall remain read-only and no duplicate master shall be created. AC4. Given a debt-specific value is created or modified, when it is submitted for activation, then F01 Maker-Checker-Approver, effective dates, active/inactive status and immutable history shall apply before the value is used. AC5. Given an approved value becomes effective, when an applicable function loads its selectors or validations, then the value shall be available only in the applicable functions: Derived from Annexure B and referenced feature metadata. | J9: Effective-dated master/reference data; source-owned IDs are reused where identified. project_program_id (source FK) | R | PRJ001 or PRG001 from the separate existing list. record_type (source value) | R | Project or Program. parent_program_id (source FK) | C | PRG001 for a project within a program. component_id (source FK, child row) | C | CMP001; only if the source provides components. responsible_organisation_id (FK M01) | R | Source agency; read-only in Debt Management. start_date / end_date (date) | R / C | Source-approved project duration. approved_cost / cost_currency_id (decimal / FK M04) | C | Source cost; not automatically the debt allocation. lifecycle_status / source_version (source fields) | R | Fetched status/version; inactive projects blocked from new links. Create/modify through F01 under Maker-Checker-Approver; approved changes apply prospectively and preserve historical references. | K9: M05 | N9: F01-F04, AC01, C01, R19-R20 | O9: Must | P9: 1 - Foundation and Configuration | Q9: Section 8.3.5 | R9: Ready for Review
A10: 0 | B10: Data Foundation and Traceability | C10: DF01 | D10: Master data and shared-source integration | E10: DF01-US06 | F10: Configuration Administrator | G10: Data foundation | H10: As a Configuration Administrator, I want to maintain or integrate M06 - Fund source / existing fund_source, so that approved debt functions use one controlled and traceable value source. | I10: AC1. Given M06 is implemented, when a value is created, fetched or synchronised, then the following ownership shall be enforced: Existing shared source. AC2. Given a record is entered or received, when it is validated, then every field, required/conditional flag, permitted value and validation documented for M06 in the Data Objects sheet shall be enforced. AC3. Given the object is source-owned, when Debt Management fetches or displays the record, then the original source ID shall be reused, source attributes shall remain read-only and no duplicate master shall be created. AC4. Given a debt-specific value is created or modified, when it is submitted for activation, then F01 Maker-Checker-Approver, effective dates, active/inactive status and immutable history shall apply before the value is used. AC5. Given an approved value becomes effective, when an applicable function loads its selectors or validations, then the value shall be available only in the applicable functions: Derived from Annexure B and referenced feature metadata. | J10: Effective-dated master/reference data; source-owned IDs are reused where identified. fund_source_id (source FK) | R | FS001. fund_source_category (source FK) | R | Budgetary resources; External loan; Domestic borrowing; Grant; Government counterpart funding. parent_fund_source_id (FK) | C | Source funding hierarchy. owner_organisation_id (FK M01) | C | Entity scope where required. coa_dimension_value_id (FK M07 dimension) | C | Existing funding-segment value, where configured. Create/modify through F01 under Maker-Checker-Approver; approved changes apply prospectively and preserve historical references. | K10: M06 | N10: F01-F04, AC01, C01, R19-R20 | O10: Must | P10: 1 - Foundation and Configuration | Q10: Section 8.3.6 | R10: Ready for Review
A11: 0 | B11: Data Foundation and Traceability | C11: DF01 | D11: Master data and shared-source integration | E11: DF01-US07 | F11: Configuration Administrator | G11: Data foundation | H11: As a Configuration Administrator, I want to maintain or integrate M07 - CoA / HoA / existing chart_of_accounts; account_dimension; account_basis_policy, so that approved debt functions use one controlled and traceable value source. | I11: AC1. Given M07 is implemented, when a value is created, fetched or synchronised, then the following ownership shall be enforced: Existing shared source. AC2. Given a record is entered or received, when it is validated, then every field, required/conditional flag, permitted value and validation documented for M07 in the Data Objects sheet shall be enforced. AC3. Given the object is source-owned, when Debt Management fetches or displays the record, then the original source ID shall be reused, source attributes shall remain read-only and no duplicate master shall be created. AC4. Given a debt-specific value is created or modified, when it is submitted for activation, then F01 Maker-Checker-Approver, effective dates, active/inactive status and immutable history shall apply before the value is used. AC5. Given an approved value becomes effective, when an applicable function loads its selectors or validations, then the value shall be available only in the applicable functions: Derived from Annexure B and referenced feature metadata. | J11: Effective-dated master/reference data; source-owned IDs are reused where identified. account_id / account_code (source ID / text) | R | Existing account reference; illustrative label BANK_CONTROL, not a prescribed code. account_name / account_class (source fields) | R | Bank, Borrowing liability, Lending receivable, Interest, Grant or expenditure classification. parent_account_id / posting_allowed (FK / boolean) | C / R | Source hierarchy and leaf/postable restriction. dimension_id / dimension_value_id (FK pair, child row) | C | Configured organisation, fund, project, economic or other dimensions. entity_id / accounting_basis_id (FK M01 / M32) | R | Use existing cash/accrual/hybrid applicability. component_id / recognition_basis_id (FK M23 / M32, child row) | C | Hybrid component-specific recognition; no second chart. effective_dates / source_status (source fields) | R | Only valid, permitted account combinations may be posted. Create/modify through F01 under Maker-Checker-Approver; approved changes apply prospectively and preserve historical references. | K11: M07 | N11: F01-F04, AC01, C01, R19-R20 | O11: Must | P11: 1 - Foundation and Configuration | Q11: Section 8.3.7 | R11: Ready for Review
A12: 0 | B12: Data Foundation and Traceability | C12: DF01 | D12: Master data and shared-source integration | E12: DF01-US08 | F12: Configuration Administrator | G12: Data foundation | H12: As a Configuration Administrator, I want to maintain or integrate M08 - Bank and account / existing bank; bank_account, so that approved debt functions use one controlled and traceable value source. | I12: AC1. Given M08 is implemented, when a value is created, fetched or synchronised, then the following ownership shall be enforced: Existing shared source. AC2. Given a record is entered or received, when it is validated, then every field, required/conditional flag, permitted value and validation documented for M08 in the Data Objects sheet shall be enforced. AC3. Given the object is source-owned, when Debt Management fetches or displays the record, then the original source ID shall be reused, source attributes shall remain read-only and no duplicate master shall be created. AC4. Given a debt-specific value is created or modified, when it is submitted for activation, then F01 Maker-Checker-Approver, effective dates, active/inactive status and immutable history shall apply before the value is used. AC5. Given an approved value becomes effective, when an applicable function loads its selectors or validations, then the value shall be available only in the applicable functions: Derived from Annexure B and referenced feature metadata. | J12: Effective-dated master/reference data; source-owned IDs are reused where identified. bank_id / branch_id (source FK) | R / C | Approved bank and branch. bank_account_id (source FK) | R | BA001; stable ID, with masked display number. owner_party_id / owner_entity_id (FK M02 / M01) | C | At least the applicable legal account owner. currency_id (FK M04) | R | Account currency. account_purpose (source FK) | R | Treasury, special/designated account, creditor or recipient account. bank_coa_id (FK M07) | C | Required for a government-owned cash account that posts to GL. settlement_channel_id / source_status (source fields) | C / R | Approved Treasury/bank channel and active status. Create/modify through F01 under Maker-Checker-Approver; approved changes apply prospectively and preserve historical references. | K12: M08 | N12: F01-F04, AC01, C01, R19-R20 | O12: Must | P12: 1 - Foundation and Configuration | Q12: Section 8.3.8 | R12: Ready for Review
A13: 0 | B13: Data Foundation and Traceability | C13: DF01 | D13: Master data and shared-source integration | E13: DF01-US09 | F13: Configuration Administrator | G13: Data foundation | H13: As a Configuration Administrator, I want to maintain or integrate M09 - Financial calendar / existing financial_year; accounting_period; business_calendar, so that approved debt functions use one controlled and traceable value source. | I13: AC1. Given M09 is implemented, when a value is created, fetched or synchronised, then the following ownership shall be enforced: Existing shared source. AC2. Given a record is entered or received, when it is validated, then every field, required/conditional flag, permitted value and validation documented for M09 in the Data Objects sheet shall be enforced. AC3. Given the object is source-owned, when Debt Management fetches or displays the record, then the original source ID shall be reused, source attributes shall remain read-only and no duplicate master shall be created. AC4. Given a debt-specific value is created or modified, when it is submitted for activation, then F01 Maker-Checker-Approver, effective dates, active/inactive status and immutable history shall apply before the value is used. AC5. Given an approved value becomes effective, when an applicable function loads its selectors or validations, then the value shall be available only in the applicable functions: Derived from Annexure B and referenced feature metadata. | J13: Effective-dated master/reference data; source-owned IDs are reused where identified. financial_year_id (source FK) | R | FY2026, using the configured year boundaries. period_id / start_date / end_date (FK / dates) | R | P2026-08 / configured period start and end. entity_id / calendar_id (FK) | R | Calendar for the accounting entity. period_status (system enum) | R | Open, Closing or Closed; controlled by authorised period operations. business_date (date) | R | Current processing date from the approved calendar service. holiday_date / holiday_name (date / text, child row) | C | Configured local holidays used by payment-date rules. adjustment_period_id (FK) | C | Authorised period for prior-period corrections. Create/modify through F01 under Maker-Checker-Approver; approved changes apply prospectively and preserve historical references. | K13: M09 | N13: F01-F04, AC01, C01, R19-R20 | O13: Must | P13: 1 - Foundation and Configuration | Q13: Section 8.3.9 | R13: Ready for Review
A14: 0 | B14: Data Foundation and Traceability | C14: DF01 | D14: Master data and shared-source integration | E14: DF01-US10 | F14: Configuration Administrator | G14: Data foundation | H14: As a Configuration Administrator, I want to maintain or integrate M10 - Users, roles and designations / existing user; role; designation; user_role_scope, so that approved debt functions use one controlled and traceable value source. | I14: AC1. Given M10 is implemented, when a value is created, fetched or synchronised, then the following ownership shall be enforced: Existing shared source. AC2. Given a record is entered or received, when it is validated, then every field, required/conditional flag, permitted value and validation documented for M10 in the Data Objects sheet shall be enforced. AC3. Given the object is source-owned, when Debt Management fetches or displays the record, then the original source ID shall be reused, source attributes shall remain read-only and no duplicate master shall be created. AC4. Given a debt-specific value is created or modified, when it is submitted for activation, then F01 Maker-Checker-Approver, effective dates, active/inactive status and immutable history shall apply before the value is used. AC5. Given an approved value becomes effective, when an applicable function loads its selectors or validations, then the value shall be available only in the applicable functions: Derived from Annexure B and referenced feature metadata. | J14: Effective-dated master/reference data; source-owned IDs are reused where identified. user_id (source FK) | R | USR001; no credential copies in Debt Management. role_id (source FK) | R | Maker, Checker, Approver, Viewer or authorised administrator. designation_id (source FK) | C | Debt Officer / Finance Controller; configurable source designation. organisation_scope_id (FK M01) | R | Permitted entity or hierarchy scope. user_id / role_id / validity (child assignment) | R | Effective-dated role assignment; one user may have several scoped roles. account_status (source enum) | R | Source active/disabled state. delegation_reference (source FK) | C | Approved temporary delegation, subject to C01 limits. Create/modify through F01 under Maker-Checker-Approver; approved changes apply prospectively and preserve historical references. | K14: M10 | N14: F01-F04, AC01, C01, R19-R20 | O14: Must | P14: 1 - Foundation and Configuration | Q14: Section 8.3.10 | R14: Ready for Review
A15: 0 | B15: Data Foundation and Traceability | C15: DF01 | D15: Master data and shared-source integration | E15: DF01-US11 | F15: Configuration Administrator | G15: Data foundation | H15: As a Configuration Administrator, I want to maintain or integrate M11 - Project expenditure category / existing expenditure_category; category_coa_map, so that approved debt functions use one controlled and traceable value source. | I15: AC1. Given M11 is implemented, when a value is created, fetched or synchronised, then the following ownership shall be enforced: Existing shared source. AC2. Given a record is entered or received, when it is validated, then every field, required/conditional flag, permitted value and validation documented for M11 in the Data Objects sheet shall be enforced. AC3. Given the object is source-owned, when Debt Management fetches or displays the record, then the original source ID shall be reused, source attributes shall remain read-only and no duplicate master shall be created. AC4. Given a debt-specific value is created or modified, when it is submitted for activation, then F01 Maker-Checker-Approver, effective dates, active/inactive status and immutable history shall apply before the value is used. AC5. Given an approved value becomes effective, when an applicable function loads its selectors or validations, then the value shall be available only in the applicable functions: Derived from Annexure B and referenced feature metadata. | J15: Effective-dated master/reference data; source-owned IDs are reused where identified. category_id (source FK) | R | EC001. parent_category_id (source FK) | C | Source category hierarchy. category_name (source text) | R | Works; Goods; Consultancy; Training; Operating costs. economic_account_id (FK M07, child row) | C | Existing economic classification or expenditure account. source_system_id / source_category_key (source fields) | R | Stable source key for project/expenditure integration. Create/modify through F01 under Maker-Checker-Approver; approved changes apply prospectively and preserve historical references. | K15: M11 | N15: F01-F04, AC01, C01, R19-R20 | O15: Must | P15: 1 - Foundation and Configuration | Q15: Section 8.3.11 | R15: Ready for Review
A16: 0 | B16: Data Foundation and Traceability | C16: DF01 | D16: Master data and shared-source integration | E16: DF01-US12 | F16: Configuration Administrator | G16: Data foundation | H16: As a Configuration Administrator, I want to maintain or integrate M12 - Instrument Type Master / debt_instrument_type, so that approved debt functions use one controlled and traceable value source. | I16: AC1. Given M12 is implemented, when a value is created, fetched or synchronised, then the following ownership shall be enforced: Configuration module. AC2. Given a record is entered or received, when it is validated, then every field, required/conditional flag, permitted value and validation documented for M12 in the Data Objects sheet shall be enforced. AC3. Given the object is source-owned, when Debt Management fetches or displays the record, then the original source ID shall be reused, source attributes shall remain read-only and no duplicate master shall be created. AC4. Given a debt-specific value is created or modified, when it is submitted for activation, then F01 Maker-Checker-Approver, effective dates, active/inactive status and immutable history shall apply before the value is used. AC5. Given an approved value becomes effective, when an applicable function loads its selectors or validations, then the value shall be available only in the applicable functions: Derived from Annexure B and referenced feature metadata. | J16: Effective-dated master/reference data; source-owned IDs are reused where identified. type_code (text) | R | LOAN; SECURITY; GRANT; GUARANTEE. type_name (text) | R | Loan; Debt security; Grant; Guarantee. subtype_master_reference (configuration reference) | R | Loan→M13; Security→M15; Grant→M26; Guarantee→M13 plus M27. portfolio_bucket (configured value) | R | Borrowing; Lending; Grant; Guarantee exposure, as applicable to transaction role. menu_route / form_definition_id (configuration reference) | R | Approved screen and applicable field set. Create/modify through F01 under Maker-Checker-Approver; approved changes apply prospectively and preserve historical references. | K16: M12 | N16: F01-F04, AC01, C01, R19-R20 | O16: Must | P16: 1 - Foundation and Configuration | Q16: Section 8.3.12 | R16: Ready for Review
... A60: 0 | B60: Data Foundation and Traceability | C60: DF02 | D60: Effective-dated configuration and control tables | E60: DF02-US13 | F60: Configuration Administrator | G60: Data foundation | H60: As a Configuration Administrator, I want to configure C13 - government_lending_scheme; scheme_condition, so that debt processing uses approved rules without changing the application core. | I60: AC1. Given C13 is configured, when a rule row is entered or imported, then every field, required/conditional flag, sample rule constraint and validation documented for C13 in the Data Objects sheet shall be enforced. AC2. Given a rule is created or changed, when it is submitted, then Maker-Checker-Approver, authority, test/simulation and effective-date controls shall apply. AC3. Given a rule version is approved, when an eligible future or open transaction is processed, then the transaction shall retain the exact version used and settled transactions or posted entries shall not be recalculated silently. AC4. Given the rule is effective, when an applicable function evaluates its controls, then it shall use the rule in the applicable functions: F35-F36 AC5. Given an eligible source event occurs, when C13 rule processing runs, then the system shall perform every trigger and action documented for C13 in the Data Objects sheet. | J60: Agreement/product/rule configuration for advanced loan and central-bank facility functions. C13 government_lending_scheme; scheme_condition: scheme_id/version (R); sanction authority/reference (R); M41 purpose, borrower category, funding source and CoA mapping (R); budget requirement (R); rate/fees/tenor/grace defaults (C); release/verification/utilisation conditions (child C); recovery/offset authority (C); effective dates (R). Example: SCHEME01 / State capital investment / sanction-specific terms. Maker creates/tests the rule, Checker validates formula and dependencies, Approver activates the effective version; actual events retain the version used. | K60: C13 | N60: F01-F04, AC01, C01, R19-R20 | O60: Must | P60: 1 - Foundation and Configuration | Q60: Section 13.2 / Annexure D | R60: Ready for Review
A61: 0 | B61: Data Foundation and Traceability | C61: DF03 | D61: Event registers, balances and traceability | E61: DF03-US01 | F61: System | G61: Data foundation | H61: As the system, I want to populate R01 - Loan Borrowing Register from approved source events, so that balances and transaction history are complete, deduplicated and traceable. | I61: AC1. Given R01 is implemented, when its schema and processing grain are reviewed, then they shall conform to: One borrowing agreement, its effective terms versions and one movement per eligible source-event line. Suggested tables: loan_borrowing; loan_terms_version; loan_borrowing_movement. AC2. Given a record or movement is written, when field validation runs, then every field, required/conditional flag and validation documented for R01 in the Data Objects sheet shall be enforced. AC3. Given an eligible event occurs, when R01 register processing runs, then every trigger, register action and linked update documented for R01 in the Data Objects sheet shall be performed. AC4. Given the same approved event is retried, when the idempotency key is evaluated, then duplicate movements shall be prevented and derived balances shall reconcile to immutable source lines. AC5. Given a correction, reversal or failed destination occurs, when the linked action is processed, then the original event shall remain available and the action and destination status shall be recorded through R19/R20. | J61: One borrowing agreement, its effective terms versions and one movement per eligible source-event line. Suggested tables: loan_borrowing; loan_terms_version; loan_borrowing_movement. loan_id / agreement_number (ID / text) | R | L001 / AGR-2026-001; unique by creditor/entity/agreement policy. creditor_id / borrower_entity_id (FK M02 / M01) | R | Government as borrower; not a subsidiary receivable. classification_id / arrangement_id / fund_source_id (FK M13 / M14 / M06) | R | External / Direct borrowing / External loan, illustrative. agreement_date / effectiveness_date / maturity_date (dates) | R | Signed, effective and final maturity dates. original_limit / approved_limit / cancelled_undrawn (decimals) | R | Example 1,000,000 / 1,000,000 / 0 in agreement currency. terms_version_id / calculation_rule_id (FK / C03) | R | Interest, repayment and charge rules; supporting terms fields in 9.23. movement_type / principal_movement (event code / decimal) | C | Drawdown +100,000; settled principal -10,000; other changes separately classified. cumulative_drawn / cumulative_principal_paid (derived decimals) | R | Derived from qualified R07 drawdowns and R10 principal settlements. undrawn_available / contractual_outstanding (derived decimals) | R | Agreement-currency available commitment and legal principal; adjusted for approved cancellation/restructuring, not FX translation. gross_carrying_amount / carrying_adjustment (derived decimals) | C | Accounting measurement separately from contractual principal; linked to R13/R18. last_schedule_version / lifecycle_status (FK R08 / system enum) | R | Current eligible schedule; Active, Matured-unpaid or Closed as applicable. F05-D/E A.5-A.6: agreement effective | CREATE agreement and approved terms version; establish authorised and undrawn limits. Do not create drawn principal. | R06 allocations; R08 schedule/forecast; R20 audit. F17 / AC03-AC04: approved evidenced drawdown | APPEND drawdown movement; DERIVE cumulative drawn, undrawn availability and contractual principal. | R07; R08-R09; eligible R17; R18-R19. F19 / AC03-AC04: principal settlement confirmed | APPEND principal repayment only for the settled principal component; DERIVE outstanding. Interest-only settlement leaves principal unchanged. | R08-R10, R12; R18-R19; forecasts/reports. F05 B / F22 / AC09: approved amendment or restructuring | VERSION terms/limit; APPEND authorised non-cash principal changes with action reference. New borrowing/repaid borrowing remain separate for refinancing. | R08, R14; affected subsidiaries flagged; accounting as configured. AC22 / F30: valuation, correction or closure | LINK R13 carrying-value/FX adjustment without changing legal principal; REVERSE/ADJUST erroneous movement; close only after reconciliation. | R13, R18-R20; eligible schedules and current reporting views. | L61: R01 | N61: F01-F04, AC01, C01, R19-R20 | O61: Must | P61: 1 - Foundation and Configuration | Q61: Section 9.2 | R61: Ready for Review
A62: 0 | B62: Data Foundation and Traceability | C62: DF03 | D62: Event registers, balances and traceability | E62: DF03-US02 | F62: System | G62: Data foundation | H62: As the system, I want to populate R02 - Government Lending / Subsidiary Loan Register from approved source events, so that balances and transaction history are complete, deduplicated and traceable. | I62: AC1. Given R02 is implemented, when its schema and processing grain are reviewed, then they shall conform to: One recipient loan/subsidiary agreement and its approved lending/recovery movements. Suggested tables: government_loan; subsidiary_terms_version; lending_movement. AC2. Given a record or movement is written, when field validation runs, then every field, required/conditional flag and validation documented for R02 in the Data Objects sheet shall be enforced. AC3. Given an eligible event occurs, when R02 register processing runs, then every trigger, register action and linked update documented for R02 in the Data Objects sheet shall be performed. AC4. Given the same approved event is retried, when the idempotency key is evaluated, then duplicate movements shall be prevented and derived balances shall reconcile to immutable source lines. AC5. Given a correction, reversal or failed destination occurs, when the linked action is processed, then the original event shall remain available and the action and destination status shall be recorded through R19/R20. | J62: One recipient loan/subsidiary agreement and its approved lending/recovery movements. Suggested tables: government_loan; subsidiary_terms_version; lending_movement. lending_id / subsidiary_agreement_ref (ID / text) | R | SL001 / subsidiary sanction or agreement. borrower_id / lending_entity_id (FK M02 / M01) | R | Recipient agency and government lender. source_instrument_id / pool_id / budget_allocation_id (source FKs) | C | Source is parent borrowing, pool or existing budget allocation. arrangement_id / terms_link_mode (FK M14 / configured value) | R | Back-to-back, Split, Pool or Budget lending; Same or Varied terms. sanctioned_amount / currency_id (decimal / FK M04) | R | 500,000 / USD, illustrative. terms_version_id / calculation_rule_id (FK / C03) | R | Independent legally approved recipient terms. disbursed_principal / recovered_principal (derived decimals) | R | Confirmed on-lending and allocated principal recoveries. contractual_receivable / accrued_receivable (derived decimals) | R / C | Legal principal and interest/fee receivables separately. gross_carrying_amount / impairment_allowance / net_carrying_amount (derived decimals) | C | Accounting values from R13/R18; net = gross less allowance. allocation_id / schedule_version_id (FK R06 / R08) | R | Funding attribution and borrower recovery schedule. F08/F09/F10/F14 A.5-A.6: subsidiary sanctioned | CREATE recipient agreement and approved terms; link each source allocation. Sanction alone is not disbursed principal. | R06; R08; Project/Program funding; R20. AC05-AC08: on-lending release confirmed | APPEND loan-disbursement movement; DERIVE disbursed amount, receivable and available limit. | R07, R06; R08-R09; B03 and common GL through R18. F20: recovery receipt approved and confirmed | APPEND only allocated principal to principal recovered; allocate interest/fees separately. | R11, R08-R09, R12; B01/B03 and R18-R19. F22 / AC09 / AC22: modification, impairment or write-off | VERSION terms; APPEND approved adjustment/write-off; LINK impairment allowance separately. Recalculate eligible unpaid schedules. | R08, R13-R14, R18-R20; do not change parent legal terms automatically. | L62: R02 | N62: F01-F04, AC01, C01, R19-R20 | O62: Must | P62: 1 - Foundation and Configuration | Q62: Section 9.3 | R62: Ready for Review
A63: 0 | B63: Data Foundation and Traceability | C63: DF03 | D63: Event registers, balances and traceability | E63: DF03-US03 | F63: System | G63: Data foundation | H63: As the system, I want to populate R03 - Securities Issue and Redemption Register from approved source events, so that balances and transaction history are complete, deduplicated and traceable. | I63: AC1. Given R03 is implemented, when its schema and processing grain are reviewed, then they shall conform to: One security series/tranche and each issue, settlement, redemption or corporate-action movement. Suggested tables: security_issue; security_tranche; security_movement; security_lineage. AC2. Given a record or movement is written, when field validation runs, then every field, required/conditional flag and validation documented for R03 in the Data Objects sheet shall be enforced. AC3. Given an eligible event occurs, when R03 register processing runs, then every trigger, register action and linked update documented for R03 in the Data Objects sheet shall be performed. AC4. Given the same approved event is retried, when the idempotency key is evaluated, then duplicate movements shall be prevented and derived balances shall reconcile to immutable source lines. AC5. Given a correction, reversal or failed destination occurs, when the linked action is processed, then the original event shall remain available and the action and destination status shall be recorded through R19/R20. | J63: One security series/tranche and each issue, settlement, redemption or corporate-action movement. Suggested tables: security_issue; security_tranche; security_movement; security_lineage. security_id / series_id / tranche_id / isin (IDs / text) | R / R / C / C | SEC001 / SERIES01 / TR01; ISIN where applicable. security_type_id / classification_id / trading_class_id (FK M15 / M13 / M16) | R | BD / Domestic / Traded, illustrative. issuer_id / holder_counterparty_id (FK M01 / M02) | R / C | Issuer; holder-level records only where source provides them. issue_date / settlement_date / maturity_date (dates) | R / C / R | Distinguish issue authority from settlement. face_value_per_unit / authorised_units / issued_units (decimal / quantities) | R | Units and face value retained separately from proceeds. issue_price / gross_proceeds / issue_cost / net_proceeds (decimals) | C | Price and net cash reconciliation at issue settlement. discount_premium / coupon_terms_version_id (decimal / FK C03) | C | Discount/premium separate from legal face amount. redeemed_units / cancelled_units / outstanding_units (derived quantities) | R | Movement-derived stock; do not count authorised unissued units. outstanding_face_value / carrying_amount (derived decimals) | R / C | Face and accounting carrying amount separately. prior_security_id / resulting_security_id / action_id (FKs, lineage row) | C | Old/new IDs for split, strips, swap or replacement. underlying_payable_id / tax_offset_reference (source FK) | C | For notes replacing payables or authorised certificate offsets. F15 subtype A.5-A.6: issue authority approved | CREATE series/tranche and terms. Set authorised amount; issued stock follows the configured evidenced issuance event. | R08 forecast; R20; no invented proceeds. AC10-AC14: evidenced issue/settlement | APPEND qualifying issue and settlement movements; DERIVE issued units, face amount, gross/net proceeds and carrying amount separately. | R07, R09; B02/B01 or non-cash B06; R18-R19. F19: coupon or redemption confirmed | APPEND coupon settlement link without reducing face value; APPEND redeemed units/principal only on redemption. | R08-R10, R12; R18-R19; stock and maturity reports. F23 / AC15: buyback, split, strips or swap effective | APPEND action and old/new lineage; cancel/replace units according to approved ratios. Confirm cash separately where required. | R14, R08; R10 if paid; B02/B06; reports. F15 B / AC22: correction, revaluation or rollover | VERSION permitted details; REVERSE/ADJUST movements; LINK R13 valuation. Rollover records old redemption and a separate new issue. | R13, R18-R20; revised eligible schedules. | L63: R03 | N63: F01-F04, AC01, C01, R19-R20 | O63: Must | P63: 1 - Foundation and Configuration | Q63: Section 9.4 | R63: Ready for Review
A64: 0 | B64: Data Foundation and Traceability | C64: DF03 | D64: Event registers, balances and traceability | E64: DF03-US04 | F64: System | G64: Data foundation | H64: As the system, I want to populate R04 - Grant Register from approved source events, so that balances and transaction history are complete, deduplicated and traceable. | I64: AC1. Given R04 is implemented, when its schema and processing grain are reviewed, then they shall conform to: One grant agreement/type and each receipt, recognition, refund or amendment movement. Suggested tables: grant_agreement; grant_condition; grant_movement. AC2. Given a record or movement is written, when field validation runs, then every field, required/conditional flag and validation documented for R04 in the Data Objects sheet shall be enforced. AC3. Given an eligible event occurs, when R04 register processing runs, then every trigger, register action and linked update documented for R04 in the Data Objects sheet shall be performed. AC4. Given the same approved event is retried, when the idempotency key is evaluated, then duplicate movements shall be prevented and derived balances shall reconcile to immutable source lines. AC5. Given a correction, reversal or failed destination occurs, when the linked action is processed, then the original event shall remain available and the action and destination status shall be recorded through R19/R20. | J64: One grant agreement/type and each receipt, recognition, refund or amendment movement. Suggested tables: grant_agreement; grant_condition; grant_movement. grant_id / agreement_ref (ID / text) | R | GR001 / donor agreement reference. grant_type_id / donor_id / recipient_entity_id (FK M26 / M02 / M01) | R | Project grant / Donor01 / receiving entity. approved_commitment / cancelled_commitment (decimals) | R | Agreement amount and approved cancellation in original currency. agreement_dates / funding_end_date (dates) | R | Signing/effectiveness and funding window. condition_set_id / recognition_rule_id (FK / C05) | R | Binding obligations or other applicable recognition policy. cumulative_received / direct_payment_value (derived decimals) | R | Government cash received and evidenced donor direct payments separately. recognised_revenue / deferred_obligation_balance (derived decimals) | C | Policy-based recognition; not all receipts automatically revenue. refund_due / refunded_amount (derived decimals) | C | Contractual refund obligation and confirmed refund paid. allocation_id / on_grant_arrangement_id (FK R06) | C | Existing Project/Program or recipient allocation. utilisation_accepted / unutilised_amount (derived decimals) | C | From R15/R17; track cash, advance and utilisation measures without mixing them. F11 subtype A.5-A.6: grant effective | CREATE grant/conditions and authorised commitment; do not treat commitment as cash or loan principal. | R06; forecast; R15 conditions; R20. F17 / AC16-AC19: grant receipt or donor direct payment confirmed | APPEND receipt/direct-payment movement and source evidence; DERIVE received funding. Apply recognition only under the approved rule. | R07; R15/R17 as relevant; B04 and R18-R19. F24 / grant recognition event: condition fulfilled | LINK accepted utilisation or obligation fulfilment; APPEND revenue/obligation movement only where policy requires it. | R15, R17; R18 if recognition changes; reports. F12: on-grant allocation/release | LINK recipient arrangement and actual release; DERIVE parent allocation use without creating a second donor receipt. | R06, R10, R15, R17; AC20. Grant amendment/refund/closure approved | VERSION conditions/limit; APPEND confirmed refund or linked correction; preserve original receipts. Close after obligations and balances reconcile. | R10, R15, R18-R20; forecasts and project views. | L64: R04 | N64: F01-F04, AC01, C01, R19-R20 | O64: Must | P64: 1 - Foundation and Configuration | Q64: Section 9.5 | R64: Ready for Review
A65: 0 | B65: Data Foundation and Traceability | C65: DF03 | D65: Event registers, balances and traceability | E65: DF03-US05 | F65: System | G65: Data foundation | H65: As the system, I want to populate R05 - Guarantee and Exposure Register from approved source events, so that balances and transaction history are complete, deduplicated and traceable. | I65: AC1. Given R05 is implemented, when its schema and processing grain are reviewed, then they shall conform to: One guarantee, its covered-component rows and borrower monitoring movements. Suggested tables: guarantee_agreement; coverage_component; borrower_service_movement. AC2. Given a record or movement is written, when field validation runs, then every field, required/conditional flag and validation documented for R05 in the Data Objects sheet shall be enforced. AC3. Given an eligible event occurs, when R05 register processing runs, then every trigger, register action and linked update documented for R05 in the Data Objects sheet shall be performed. AC4. Given the same approved event is retried, when the idempotency key is evaluated, then duplicate movements shall be prevented and derived balances shall reconcile to immutable source lines. AC5. Given a correction, reversal or failed destination occurs, when the linked action is processed, then the original event shall remain available and the action and destination status shall be recorded through R19/R20. | J65: One guarantee, its covered-component rows and borrower monitoring movements. Suggested tables: guarantee_agreement; coverage_component; borrower_service_movement. guarantee_id / approval_reference (ID / text) | R | GUA001 / guarantee sanction. underlying_loan_reference / borrower_id / lender_id (source ID / FK M02) | R | Agency loan and parties; not a new government borrowing ID. guarantor_entity_id / classification_id (FK M01 / M13) | R | Guarantor and domestic/external classification. coverage_id / coverage_percentage / coverage_cap (FK M27 / decimals) | R / R / C | Partial / 80% / 800,000 illustrative; enforce cap and eligible components. covered_component_id (FK M23, child row) | R | Principal, interest or specified charges only as authorised. valid_from / expiry_date / claim_deadline (dates) | R / R / C | Coverage and permitted claim dates. borrower_drawn / borrower_principal_paid / borrower_overdue (derived decimals) | R | Borrower actuals, supported by agency/lender evidence. covered_drawn_exposure / remaining_cap (derived decimals) | R | Apply agreement coverage rules; no assumed reinstatement after payment. recognised_guarantee_liability (derived decimal) | C | Separate accounting liability measured through R13/R18 when policy requires. guarantee_fee_rule / collateral_reference (FK C03 / source ID) | C | Fee and security conditions. invocation_id / guarantee_status (FK R16 / system enum) | C / R | Active, Expired, Invoked or Released under approved conditions. F13 A.5-A.6: guarantee effective | CREATE guarantee and component coverage; DERIVE authorised coverage and monitoring baseline. | R08 fee/monitoring schedule; R20; applicable measurement via R13. F13 B.2-B.5: borrower drawdown/payment verified | APPEND borrower actual; DERIVE covered drawn exposure, remaining eligible cap and overdue profile. Do not post government cash. | R08 monitoring, R12 where relevant; guarantee reports. AC21: approved periodic measurement or fee accrual | LINK R13 recognised liability separately from exposure; LINK R09 guarantee-fee dues. | B05/B06 only if accounting required; R18-R19. Invocation approval and government settlement | LINK R16 claim/obligation/payment; DERIVE residual exposure under the guarantee terms, avoiding overlapping active and invoked exposure. | R16, R10; separate recourse/recovery; R18-R19. Coverage amendment, expiry or release | VERSION approved coverage; restrict new claims according to validity/terms; release only resolved exposure. Preserve pending valid claims. | R08, R16, R20; alerts and contingent-liability reports. | L65: R05 | N65: F01-F04, AC01, C01, R19-R20 | O65: Must | P65: 1 - Foundation and Configuration | Q65: Section 9.6 | R65: Ready for Review
A66: 0 | B66: Data Foundation and Traceability | C66: DF03 | D66: Event registers, balances and traceability | E66: DF03-US06 | F66: System | G66: Data foundation | H66: As the system, I want to populate R06 - Funding Allocation / Pool Register from approved source events, so that balances and transaction history are complete, deduplicated and traceable. | I66: AC1. Given R06 is implemented, when its schema and processing grain are reviewed, then they shall conform to: One source-to-recipient/project allocation and child source-share rows for every attributed release. Suggested tables: funding_allocation; pool_source; recipient_allocation; funding_attribution. AC2. Given a record or movement is written, when field validation runs, then every field, required/conditional flag and validation documented for R06 in the Data Objects sheet shall be enforced. AC3. Given an eligible event occurs, when R06 register processing runs, then every trigger, register action and linked update documented for R06 in the Data Objects sheet shall be performed. AC4. Given the same approved event is retried, when the idempotency key is evaluated, then duplicate movements shall be prevented and derived balances shall reconcile to immutable source lines. AC5. Given a correction, reversal or failed destination occurs, when the linked action is processed, then the original event shall remain available and the action and destination status shall be recorded through R19/R20. | J66: One source-to-recipient/project allocation and child source-share rows for every attributed release. Suggested tables: funding_allocation; pool_source; recipient_allocation; funding_attribution. allocation_id / pool_id (ID / FK) | R / C | ALLOC001 / POOL001. source_instrument_id / budget_allocation_id (FKs) | C | At least the applicable debt/grant source or budget funding reference. recipient_id / subsidiary_id (FK M02 / R02) | C | Agency and subsidiary agreement where applicable. project_program_id / component_id (FK M05) | C | Existing source project/program/component. approved_amount / allocation_currency_id (decimal / FK M04) | R | 1,000,000 / USD, illustrative. source_currency_amount / conversion_rate_id (decimal / FK C02) | C | Required where allocation and source currencies differ. funding_start / funding_end (dates) | R | Approved eligibility period. reserved_amount / released_amount / available_amount (derived decimals) | R | Approved allocation less used and applicable reservations; no cash implied by allocation. source_share / attributed_event_id / attributed_amount (decimal / FK / decimal, child row) | C | Source share for each funding movement; attributed totals equal the released amount. reallocation_from_id / cancellation_amount (FK / decimal) | C | Approved movement of unused allocation or cancellation. F07/F08/F09/F10/F12/F14: allocation approved | CREATE source/recipient allocation and pool-source rows; validate total limits and currency conversions. | R01/R02/R04 links; Project/Program financing; forecast. Eligible claim/reservation or evidenced release | RESERVE approved pending amount where configured; on confirmation RELEASE reservation, APPEND used funding and source attribution. | R07/R10; R02/R15; R17 financing views. Approved reallocation or source-share amendment | VERSION unused future allocation; APPEND any authorised transfer of limit. Do not overwrite attribution of settled movements. | Limits, selectors and forecasts; R20; revalidate pending transactions. Confirmed return/refund or allocation cancellation | APPEND qualifying refund/reversal or unused cancellation; DERIVE availability only when the agreement permits re-use. | R04/R11/R15; R18 for financial effects; R19 reconciliation. | L66: R06 | N66: F01-F04, AC01, C01, R19-R20 | O66: Must | P66: 1 - Foundation and Configuration | Q66: Section 9.7 | R66: Ready for Review
A67: 0 | B67: Data Foundation and Traceability | C67: DF03 | D67: Event registers, balances and traceability | E67: DF03-US07 | F67: System | G67: Data foundation | H67: As the system, I want to populate R07 - Disbursement and Receipt Register from approved source events, so that balances and transaction history are complete, deduplicated and traceable. | I67: AC1. Given R07 is implemented, when its schema and processing grain are reviewed, then they shall conform to: One evidenced funding/receipt/release transaction, with component and allocation child lines. Suggested tables: funding_transaction; funding_component; funding_evidence. AC2. Given a record or movement is written, when field validation runs, then every field, required/conditional flag and validation documented for R07 in the Data Objects sheet shall be enforced. AC3. Given an eligible event occurs, when R07 register processing runs, then every trigger, register action and linked update documented for R07 in the Data Objects sheet shall be performed. AC4. Given the same approved event is retried, when the idempotency key is evaluated, then duplicate movements shall be prevented and derived balances shall reconcile to immutable source lines. AC5. Given a correction, reversal or failed destination occurs, when the linked action is processed, then the original event shall remain available and the action and destination status shall be recorded through R19/R20. | J67: One evidenced funding/receipt/release transaction, with component and allocation child lines. Suggested tables: funding_transaction; funding_component; funding_evidence. transaction_id / direction / transaction_type (ID / enums) | R | IN or OUT; Drawdown, Issue proceeds, Grant receipt or Lending release. disbursement_method_id (FK M25) | R | Reimbursement, Cash advance, Direct payment, Special account or approved Other. payer_id / payee_id (FK M02) | R | Actual source and beneficiary. gross_amount / withheld_charge / net_amount (decimals) | R | 100,000 / 1,000 / 99,000 illustrative; retain component reconciliation. principal_component / fee_component (decimal, child lines M23) | C | Separate principal from fees deducted at source. bank_account_id / value_date (FK M08 / date) | C / R | Bank reference for government cash; direct-payment evidence instead where non-cash. bank_reference / settlement_reference / confirmation_date (source references / date) | R | Confirmed receipt/payment or authoritative direct-payment advice. expense_reference / advance_reference (source FKs) | C | Required for reimbursement, direct payment or advance liquidation linkage. forecast_line_id / allocation_id (FK / R06) | C | Match actual to forecast without converting the forecast into another actual. evidence_status / confirmed_amount (system status / decimal) | R | Confirmed, Part-confirmed or Exception; only validated confirmed amounts affect actuals. F17: request saved/submitted | CREATE workflow record and evidence links only; keep approved actual views unchanged. | R20; proposed R18 event if relevant. Approval plus validated receipt/settlement evidence | APPEND confirmed movement once; split gross/net/principal/fees; DERIVE related funding balances. | R01-R04 as appropriate; R06, R08, R15/R17; R18-R19. Approved reimbursement or donor/lender direct payment | LINK original expenditure/payment evidence and financing share; record correct bank/non-bank direction. | R17; eligible R15; do not repeat already posted expenditure. Part confirmation, rejection, correction or reversal | APPEND only new confirmed amount; retain failed/unconfirmed portion. REVERSE/ADJUST approved error with original reference. | Affected funding/schedule registers; R18-R20; source confirmation required for cash reversal. | L67: R07 | N67: F01-F04, AC01, C01, R19-R20 | O67: Must | P67: 1 - Foundation and Configuration | Q67: Section 9.8 | R67: Ready for Review
A68: 0 | B68: Data Foundation and Traceability | C68: DF03 | D68: Event registers, balances and traceability | E68: DF03-US08 | F68: System | G68: Data foundation | H68: As the system, I want to populate R08 - Debt Service / Recovery Schedule Register from approved source events, so that balances and transaction history are complete, deduplicated and traceable. | I68: AC1. Given R08 is implemented, when its schema and processing grain are reviewed, then they shall conform to: One instrument schedule version and one due-date/component line, linked to actual settlements. Suggested tables: service_schedule; schedule_version; schedule_line; settlement_allocation. AC2. Given a record or movement is written, when field validation runs, then every field, required/conditional flag and validation documented for R08 in the Data Objects sheet shall be enforced. AC3. Given an eligible event occurs, when R08 register processing runs, then every trigger, register action and linked update documented for R08 in the Data Objects sheet shall be performed. AC4. Given the same approved event is retried, when the idempotency key is evaluated, then duplicate movements shall be prevented and derived balances shall reconcile to immutable source lines. AC5. Given a correction, reversal or failed destination occurs, when the linked action is processed, then the original event shall remain available and the action and destination status shall be recorded through R19/R20. | J68: One instrument schedule version and one due-date/component line, linked to actual settlements. Suggested tables: service_schedule; schedule_version; schedule_line; settlement_allocation. schedule_id / schedule_version / schedule_line_id (IDs / integer) | R | SCH001 / 1 / SCH001-L01. schedule_role (configured value) | R | Borrowing service; Lending recovery; Security coupon/redemption; Guarantee fee; Borrower monitoring. terms_version_id / rate_version_id / calculation_run_id (FKs) | R / C / R | Reproducible approved inputs. due_date / period_start / period_end (dates) | R / C / C | Due date and interest/fee accrual period. component_id / scheduled_amount (FK M23 / decimal) | R | INTEREST / 5,000 illustrative. principal_base / rate / day_count_id (decimal / decimal / M21) | C | Required calculation inputs for interest/fees. settled_amount / reserved_amount / waived_amount (derived decimals) | R | Actual allocations, pending claims and authorised reductions tracked separately. balance_due / overdue_days (derived decimal / integer) | R | Due less valid settlements/waivers/adjustments; reservations do not count as paid. superseded_line_id / source_amendment_id (FKs) | C | Revision lineage; settled instalments remain unchanged. forecast_actual_indicator / settlement_id (system indicator / FK) | R / C | Scheduled due and linked actual allocation kept distinct. F18 A.5-A.6: baseline schedule approved | CREATE schedule/version and component lines using approved terms and rates. | Claim-selection lists; F16/F26 forecasts; maturity alerts; R20. Approved term/rate reset, drawdown or restructuring | VERSION eligible unpaid schedule lines; retain settled portions; flag or block in-flight claims needing revision. | R01-R03, R09, R10, R14; forecast baselines flagged for review. Confirmed payment/recovery allocation | APPEND settlement link by component; DERIVE paid/recovered and balance due. Remove corresponding reservation only once. | R10/R11; R12 ageing; instrument principal only for principal. Due date passes or waiver/correction approved | DERIVE overdue profile from current dues; LINK R12 assessment/waiver; REVERSE/ADJUST erroneous allocation without deleting prior settlement. | R12; alerts; eligible R18-R19. | L68: R08 | N68: F01-F04, AC01, C01, R19-R20 | O68: Must | P68: 1 - Foundation and Configuration | Q68: Section 9.9 | R68: Ready for Review
A69: 0 | B69: Data Foundation and Traceability | C69: DF03 | D69: Event registers, balances and traceability | E69: DF03-US09 | F69: System | G69: Data foundation | H69: As the system, I want to populate R09 - Interest, Fees and Accrual Register from approved source events, so that balances and transaction history are complete, deduplicated and traceable. | I69: AC1. Given R09 is implemented, when its schema and processing grain are reviewed, then they shall conform to: One instrument/component/calculation period and each approved accrual, amortisation or settlement movement. Suggested tables: component_calculation; accrual_movement; accrual_settlement. AC2. Given a record or movement is written, when field validation runs, then every field, required/conditional flag and validation documented for R09 in the Data Objects sheet shall be enforced. AC3. Given an eligible event occurs, when R09 register processing runs, then every trigger, register action and linked update documented for R09 in the Data Objects sheet shall be performed. AC4. Given the same approved event is retried, when the idempotency key is evaluated, then duplicate movements shall be prevented and derived balances shall reconcile to immutable source lines. AC5. Given a correction, reversal or failed destination occurs, when the linked action is processed, then the original event shall remain available and the action and destination status shall be recorded through R19/R20. | J69: One instrument/component/calculation period and each approved accrual, amortisation or settlement movement. Suggested tables: component_calculation; accrual_movement; accrual_settlement. calculation_id / component_id (ID / FK M23) | R | CALC001 / INTEREST. period_start / period_end / day_count_id (dates / FK M21) | R | Accrual interval and exact convention. base_amount / charge_basis_id (decimal / FK M24) | R | Outstanding principal, undrawn commitment or other authorised basis. interest_type_id / benchmark_rate_id / spread (FK M17 / C02 / decimal) | C | Fixed/floating inputs with version and unit. calculated_amount / approved_amount (decimals) | R | Proposed and approved component calculation. amortisation_amount / discount_premium_reference (decimal / FK R03) | C | Security discount/premium/eligible cost treatment under C05. receivable_payable_direction (configured value) | R | RECEIVABLE or PAYABLE; never infer from a positive amount alone. recognised_accrual / unrecognised_control_amount (derived decimals) | C | Accounting versus operational amounts according to basis. settled_amount / reversed_amount / component_balance (derived decimals) | R | Derived from eligible movements and R10/R11 allocation. calculation_rule_version / rounding_difference (FK C03 / decimal) | R | Traceable formula and rounding result. Approved calculation/accrual batch effective | APPEND component calculation and eligible accrual movement; retain full inputs. | R08 component dues; R18 for recognised accrual; books B02/B03/B05/B06. Approved amortisation/penalty/fee recognition | APPEND separately coded movement; do not merge amortisation or penalty into legal principal. | R03/R12/R13 as applicable; R18-R19. Confirmed payment/recovery allocated | APPEND settlement allocation; DERIVE component outstanding; prevent payment from creating the expense a second time where already accrued. | R10/R11; R08 and R12; R18 link. Rate correction, waiver or calculation error approved | REVERSE/ADJUST affected recognised movement; regenerate only eligible open calculations. Preserve prior rate and calculation version. | R08/R12; R18-R20; published outputs revised through versioning. | L69: R09 | N69: F01-F04, AC01, C01, R19-R20 | O69: Must | P69: 1 - Foundation and Configuration | Q69: Section 9.10 | R69: Ready for Review
A70: 0 | B70: Data Foundation and Traceability | C70: DF03 | D70: Event registers, balances and traceability | E70: DF03-US10 | F70: System | G70: Data foundation | H70: As the system, I want to populate R10 - Claim and Payment Register from approved source events, so that balances and transaction history are complete, deduplicated and traceable. | I70: AC1. Given R10 is implemented, when its schema and processing grain are reviewed, then they shall conform to: One Claim Request with component reservations and one row per payment instruction/confirmation. Suggested tables: claim_request; claim_component; payment_instruction; payment_confirmation. AC2. Given a record or movement is written, when field validation runs, then every field, required/conditional flag and validation documented for R10 in the Data Objects sheet shall be enforced. AC3. Given an eligible event occurs, when R10 register processing runs, then every trigger, register action and linked update documented for R10 in the Data Objects sheet shall be performed. AC4. Given the same approved event is retried, when the idempotency key is evaluated, then duplicate movements shall be prevented and derived balances shall reconcile to immutable source lines. AC5. Given a correction, reversal or failed destination occurs, when the linked action is processed, then the original event shall remain available and the action and destination status shall be recorded through R19/R20. | J70: One Claim Request with component reservations and one row per payment instruction/confirmation. Suggested tables: claim_request; claim_component; payment_instruction; payment_confirmation. claim_request_no / claim_type (ID / configured value) | R | CR2026-0001 / Debt repayment, Grant transfer/refund or Guarantee settlement. beneficiary_id / beneficiary_account_id (FK M02 / M08) | R / C | Approved payee and payment account. schedule_line_id / component_id / claim_amount (FK R08 / M23 / decimal, child row) | C / R / R | Principal, Interest, Penalty or charge; interest-only allowed. due_amount / prior_paid / reserved_elsewhere / available_to_claim (derived decimals) | R | Prevent over-claiming across concurrent requests. budget_allocation_id / fund_source_id / account_dimensions (source FKs) | C | Existing budget and CoA mappings where applicable. approved_claim_amount / reserved_amount (decimals) | C | Populate on approval/reservation under the configured workflow. treasury_reference / instruction_id / instruction_date (source IDs / date) | C | Sent-to-Treasury and payment instruction lineage. confirmation_id / settlement_date / settled_amount (source ID / date / decimal) | C | One line per confirmed partial/full settlement. failed_amount / unpaid_balance / cancellation_reference (derived decimals / FK) | C | Failure is not settlement; cancellation requires Treasury acknowledgement where sent. claim_status / payment_status (system enums) | R | Separate approval state from Payment Pending, Part Paid, Paid, Failed or Cancelled. F19: Maker creates Claim Request | CREATE request and component lines; validate latest due/paid/reserved balances; no cash or principal effect. | R20; source schedule reference. Checker/Approver complete; claim released to Treasury | RESERVE authorised amount as configured; APPEND Treasury instruction/reference. Do not mark paid. | R08 reservation; budget/claim service; R18 only for separately eligible obligation recognition. Treasury/bank confirms partial or full payment | APPEND confirmation once; allocate components, RELEASE settled reservation and DERIVE unpaid balance. | R01/R03 principal as appropriate; R08-R09/R12; R16 for invocation; R18-R19. Unpaid claim amended/cancelled or instruction fails | VERSION authorised unpaid claim after coordination; RELEASE reservation only when cancellation/failure outcome is confirmed. Retain history. | R08, budget/claim source, R19 exceptions; no fictitious bank reversal. Paid claim correction or genuine bank reversal | APPEND linked adjustment/reversal under approved evidence; preserve original instruction and confirmation. | All affected due/balance registers, books/GL via R18, R19 reconciliation. | L70: R10 | N70: F01-F04, AC01, C01, R19-R20 | O70: Must | P70: 1 - Foundation and Configuration | Q70: Section 9.11 | R70: Ready for Review
A71: 0 | B71: Data Foundation and Traceability | C71: DF03 | D71: Event registers, balances and traceability | E71: DF03-US11 | F71: System | G71: Data foundation | H71: As the system, I want to populate R11 - Borrower / Other Recovery Register from approved source events, so that balances and transaction history are complete, deduplicated and traceable. | I71: AC1. Given R11 is implemented, when its schema and processing grain are reviewed, then they shall conform to: One confirmed recovery receipt and one allocation row per instrument/instalment/component. Suggested tables: recovery_receipt; recovery_allocation; recovery_adjustment. AC2. Given a record or movement is written, when field validation runs, then every field, required/conditional flag and validation documented for R11 in the Data Objects sheet shall be enforced. AC3. Given an eligible event occurs, when R11 register processing runs, then every trigger, register action and linked update documented for R11 in the Data Objects sheet shall be performed. AC4. Given the same approved event is retried, when the idempotency key is evaluated, then duplicate movements shall be prevented and derived balances shall reconcile to immutable source lines. AC5. Given a correction, reversal or failed destination occurs, when the linked action is processed, then the original event shall remain available and the action and destination status shall be recorded through R19/R20. | J71: One confirmed recovery receipt and one allocation row per instrument/instalment/component. Suggested tables: recovery_receipt; recovery_allocation; recovery_adjustment. recovery_id / receipt_id / bank_reference (ID / source IDs) | R | REC001 linked to a confirmed receipt, not an unverified manual statement. payer_id / receivable_instrument_id (FK M02 / R02 or R16) | R | Borrower or recourse debtor. receipt_date / value_date / receipt_amount (dates / decimal) | R | Original confirmed cash event. bank_account_id / receipt_currency_id (FK M08 / M04) | R | Approved government receipt account and original currency. schedule_line_id / component_id / allocated_amount (FK R08 / M23 / decimal, child row) | C / R / R | Allocation to principal, interest, fees or penalty. unapplied_amount / excess_amount (derived decimals) | R | Unallocated or overpaid receipt; not principal reduction until matched. recourse_id / on_grant_refund_id (FKs) | C | Non-ordinary-loan recovery origin. refund_claim_id / reallocation_id / reversal_id (FKs) | C | Link approved correction or refund; no receipt deletion. recovery_status / remaining_receivable (system enum / derived decimal) | R | Unapplied, Part Applied or Applied; outstanding receivable after valid allocations. F20: receipt evidenced and allocation approved | CREATE receipt link; APPEND component allocations once; DERIVE principal/component recovery and unapplied amount. | R02/R16; R08-R09/R12; B01/B03/B05; R18-R19. Receipt unmatched or partially allocatable | APPEND unapplied balance/exception; retain cash/control accounting as configured without reducing the wrong loan. | R19 matching queue; R18 source voucher link. Correct allocation approved | APPEND reversal of old allocation and new allocation; retain original receipt amount/reference and prevent a second cash entry. | R02/R08/R09/R12/R16; R18 only for required reclassification. Refund or bank reversal confirmed | APPEND linked refund/reversal with evidence; restore receivable only as justified by the event. | R10 for outgoing refund; R18-R20; current recovery reports. | L71: R11 | N71: F01-F04, AC01, C01, R19-R20 | O71: Must | P71: 1 - Foundation and Configuration | Q71: Section 9.12 | R71: Ready for Review
A72: 0 | B72: Data Foundation and Traceability | C72: DF03 | D72: Event registers, balances and traceability | E72: DF03-US12 | F72: System | G72: Data foundation | H72: As the system, I want to populate R12 - Arrears, Penalty and Waiver Register from approved source events, so that balances and transaction history are complete, deduplicated and traceable. | I72: AC1. Given R12 is implemented, when its schema and processing grain are reviewed, then they shall conform to: One overdue instrument/schedule/component position and its assessed/waived/settled movements. Suggested tables: arrears_position; penalty_assessment; waiver_movement. AC2. Given a record or movement is written, when field validation runs, then every field, required/conditional flag and validation documented for R12 in the Data Objects sheet shall be enforced. AC3. Given an eligible event occurs, when R12 register processing runs, then every trigger, register action and linked update documented for R12 in the Data Objects sheet shall be performed. AC4. Given the same approved event is retried, when the idempotency key is evaluated, then duplicate movements shall be prevented and derived balances shall reconcile to immutable source lines. AC5. Given a correction, reversal or failed destination occurs, when the linked action is processed, then the original event shall remain available and the action and destination status shall be recorded through R19/R20. | J72: One overdue instrument/schedule/component position and its assessed/waived/settled movements. Suggested tables: arrears_position; penalty_assessment; waiver_movement. arrears_id / schedule_line_id (ID / FK R08) | R | AR001 linked to a specific due component. component_id / original_due_date (FK M23 / date) | R | Principal, interest, fee or penalty; original due date retained. overdue_base / overdue_days / ageing_bucket (derived values) | R | Unpaid due at as-of date; example 31-60 days using configured buckets. assessment_id / penalty_rule_id (ID / FK C03) | C | Penalty assessment; not every overdue amount automatically attracts penalty. assessment_period / rate / assessed_penalty (dates / decimals) | C | Approved contract/rule inputs. waiver_id / waiver_authority / waived_amount (ID / evidence / decimal) | C | Approved waiver scope and amount by component. settled_amount / adjusted_amount / remaining_arrears (derived decimals) | R | Settlements, valid adjustments and balance retained separately. as_of_date / resolution_status (date / system enum) | R | Reproducible ageing snapshot and current resolution. Scheduled daily ageing under approved rule | CREATE/DERIVE current overdue position from R08 and settlements; retain as-of snapshots where reports require them. | Alerts, F21 work queue and reports; no automatic principal change. F21: penalty assessment approved | APPEND authorised penalty movement and calculation reference; separate from overdue principal. | R09; R08 due component; R18 if recognised. Confirmed late payment/recovery | APPEND settlement link and DERIVE residual arrears/ageing by component. | R10/R11; R08; alerts resolved as appropriate. Waiver, adjustment or reversal approved | APPEND waiver/correction with authority; update eligible dues and accounting treatment without recording cash payment. | R08-R09; R18-R20; revised arrears reports. | L72: R12 | N72: F01-F04, AC01, C01, R19-R20 | O72: Must | P72: 1 - Foundation and Configuration | Q72: Section 9.13 | R72: Ready for Review
... A84: 0 | B84: Data Foundation and Traceability | C84: DF03 | D84: Event registers, balances and traceability | E84: DF03-US24 | F84: System | G84: Data foundation | H84: As the system, I want to populate R24 - Central-bank Facility, Daily Utilisation and Collateral Register from approved source events, so that balances and transaction history are complete, deduplicated and traceable. | I84: AC1. Given R24 is implemented, when its schema and processing grain are reviewed, then they shall conform to: One approved source-event/version at the grain defined in Section 13.3; balances are derived from immutable movements. AC2. Given a record or movement is written, when field validation runs, then every field, required/conditional flag and validation documented for R24 in the Data Objects sheet shall be enforced. AC3. Given an eligible event occurs, when R24 register processing runs, then every trigger, register action and linked update documented for R24 in the Data Objects sheet shall be performed. AC4. Given the same approved event is retried, when the idempotency key is evaluated, then duplicate movements shall be prevented and derived balances shall reconcile to immutable source lines. AC5. Given a correction, reversal or failed destination occurs, when the linked action is processed, then the original event shall remain available and the action and destination status shall be recorded through R19/R20. | J84: One approved source-event/version at the grain defined in Section 13.3; balances are derived from immutable movements. facility_id / borrower / central_bank / bank_account (R) | CBF01 with M01/M02/M08 references; linked R01 instrument ID, not another independently counted borrowing. facility_type / rule_version / limit_period (R) | M42 and C12 effective rules; central and state profiles distinct. authorised_limit / value_date / source_advice_id (R/R/C) | Validated authority and daily bank evidence; source row key stable across retries. opening / drawings / principal_repaid / reclass / closing (derived; R) | Opening + drawings - repayments +/- authorised reclass = closing; do not count the same balance under WMA and OD. benchmark / spread / rate_tier / interest / maturity (C) | Dated C02/C12 inputs and daily R09 calculation; retain value date versus posting date. OD_continuous_days / OD_period_days / breach_type (C) | Configured calendar, period boundary and reset rules; breaches retained after clearance. security_id / custodian / pledged_units / valuation_date (child; C) | Required for secured facility; reference existing security/custody record and other encumbrances. eligible_value / haircut / prior_pledge / drawing_power (child; C) | Derive available collateral capacity from dated C12 rule; aggregate only unencumbered eligible coverage. sweep_ref / settlement_ref / R18_voucher / restriction_ref (C) | Authoritative repayment and journal; restriction/clearance evidence, no duplicate manual payment. available_headroom / overdue / reconciliation_result (derived; R) | Daily facility limits, interest and bank reconciliation; show unreconciled observations separately. F37 setup/limit version approved | CREATE/VERSION facility authority and collateral rules, no cash movement. | R01 reference; headroom/forecast Central-bank advice/daily statement received | APPEND evidenced source movement or pending observation; DERIVE daily balances; alert actual exposure even while exceptions await review. | R07/R01; R09; R19/R20 OD trigger or daily counter update | DERIVE OD use and counters under C12; APPEND breach/alert; do not invent a second drawdown on reclassification. | F38; R08/R09; Treasury alerts Confirmed sweep/repayment | APPEND one principal/interest settlement allocation; DERIVE outstanding and clearance. | R10/R01/R08/R09; R18 Collateral valuation/pledge/release approved | VERSION pledge and valuation; DERIVE drawing power; flag shortage and restrict further requested use where required. | Headroom; R19; alerts; no cash Rate/value-date correction or closure | APPEND approved differences; recalculate affected daily interest/counters, reconcile and preserve all advice history. | R01/R08/R09/R18-R20; reports | L84: R24 | N84: F01-F04, AC01, C01, R19-R20 | O84: Must | P84: 1 - Foundation and Configuration | Q84: Section 13.3.4 | R84: Ready for Review
A85: 1 | B85: 1. General | C85: F01 | D85: Maintain master values | E85: F01-US01 | F85: Maker | G85: First-time | H85: As a Maker, I want to create, save and submit Maintain master values, so that the transaction can enter the controlled approval workflow. | I85: AC1. Given an authorised Maker is working with the new request, when the Maintain master values action is performed, then the system shall maker shall allow the user to log in, open Configuration > Debt Masters and select Add New Value. AC2. Given an authorised Maker is working with the new request, when the Maintain master values action is performed, then the system shall maker shall select the master, enter its code, name, description, category and effective dates, and link any required parent value. AC3. Given an authorised Maker is working with the new request, when the Maintain master values action is performed, then the system shall maker shall select Save Draft, review the new value and submit it to the Checker. AC4. Given the request is incomplete, when Save Draft is selected, then the system shall retain it as Draft, assign a request/version reference and make no change to approved balances, registers, books or the common GL. AC5. Given all mandatory validations pass, when Submit is selected, then the status shall become Submitted, the request shall enter the configured Checker queue and the submission shall be appended to R20. | J85: Maker should be able to log in, open Configuration > Debt Masters and select Add New Value. Maker should select the master, enter its code, name, description, category and effective dates, and link any required parent value. Maker should select Save Draft, review the new value and submit it to the Checker. | K85: M01, M35 | N85: M01, M35 | O85: Must | P85: 1 - Foundation and Configuration | Q85: 1.5.1 | R85: Ready for Review
A86: 1 | B86: 1. General | C86: F01 | D86: Maintain master values | E86: F01-US02 | F86: Checker | G86: First-time | H86: As a Checker, I want to verify a new Maintain master values request, so that only complete and valid requests proceed for authorisation. | I86: AC1. Given an authorised Checker is working with the new request, when the Maintain master values action is performed, then the system shall checker shall log in, open Pending Verification and check code uniqueness, permitted values, parent linkage and effective dates. AC2. Given an authorised Checker is working with the new request, when the Maintain master values action is performed, then the system shall the. AC3. Given an authorised Checker is working with the new request, when the Maintain master values action is performed, then the system shall checker shall return errors with comments or select Verify and Forward. AC4. Given the request is in Pending Verification, when the Checker acts, then the system shall enforce segregation of duties, show supporting evidence and relevant source/current values, and prevent the Maker from checking the same request. AC5. Given a validation fails, when Return is selected, then comments shall be mandatory and the request shall return to the Maker; when all checks pass, Verify and Forward shall place the checked version in the Approver queue and append the decision to R20. | J86: Checker should log in, open Pending Verification and check code uniqueness, permitted values, parent linkage and effective dates. The Checker should return errors with comments or select Verify and Forward. | K86: M01, M35 | N86: M01, M35 | O86: Must | P86: 1 - Foundation and Configuration | Q86: 1.5.1 | R86: Ready for Review
A87: 1 | B87: 1. General | C87: F01 | D87: Maintain master values | E87: F01-US03 | F87: Approver | G87: First-time | H87: As a Approver, I want to authorise a checked Maintain master values request, so that the approved version becomes authoritative within delegated powers. | I87: AC1. Given an authorised Approver is working with the new request, when the Maintain master values action is performed, then the system shall approver shall log in, open Pending Approval, review the checked record and supporting evidence, and approve, return or reject the request. Approval shall activate the checked master value. AC2. Given a Checker-verified request, when the Approver reviews it, then configured authority, effective date, evidence and the checked version shall be displayed; the Maker or Checker of the request shall not approve it. AC3. Given the checked request is open in the Approver queue, when the Approver selects Approve, Return or Reject, then the system shall record the decision, comments, timestamp and authority in R20; only an approved effective version may update live records. | J87: Approver should log in, open Pending Approval, review the checked record and supporting evidence, and approve, return or reject the request. Approval should activate the checked master value. | K87: M01, M35 | N87: M01, M35 | O87: Must | P87: 1 - Foundation and Configuration | Q87: 1.5.1 | R87: Ready for Review
A88: 1 | B88: 1. General | C88: F01 | D88: Maintain master values | E88: F01-US04 | F88: System | G88: First-time | H88: As the system, I want to apply an approved Maintain master values event to every affected record, so that registers, schedules, integrations, books, GL and reports remain consistent and traceable. | I88: AC1. Given an authorised System is working with the new request, when the Maintain master values action is performed, then the system shall the. AC2. Given an authorised System is working with the new request, when the Maintain master values action is performed, then the system shall system shall make the approved value available in the dropdowns, validations and report filters of the functions listed against that master. AC3. Given an approved source event, when downstream processing runs or is retried, then the same source/version/idempotency key shall update each destination once only, with Success, Pending, Failed or Not Applicable recorded separately in R20 and reconciliation exceptions in R19. AC4. Given any destination update has failed, when the processing result is displayed or retried, then successful destinations shall remain traceable, the failure shall be visible and retryable, and the request shall not be incorrectly represented as fully completed. | J88: The The The The The The system should make the approved value available in the dropdowns, validations and report filters of the functions listed against that master. | K88: M01, M35 | N88: M01, M35 | O88: Must | P88: 1 - Foundation and Configuration | Q88: 1.5.1 | R88: Ready for Review
A89: 1 | B89: 1. General | C89: F01 | D89: Maintain master values | E89: F01-US05 | F89: Maker | G89: Existing | H89: As a Maker, I want to find, review and request a controlled modification to Maintain master values, so that existing records can be corrected or amended with evidence and an effective date. | I89: AC1. Given an authorised Maker is working with the approved existing record and its history, when the Maintain master values action is performed, then the system shall maker shall allow the user to log in, open Configuration > Debt Masters, search by master name, code or value and view the approved record and history. AC2. Given an authorised Maker is working with the approved existing record and its history, when the Maintain master values action is performed, then the system shall maker shall select Request Modification, amend the name, description, category or effective dates, or request deactivation; then enter the reason, save and submit. AC3. Given an approved record is modified, when the Maker submits the revision, then reason, effective date, amendment/evidence and before/after values shall be mandatory, and the existing approved version shall remain effective until approval and the configured effective date. | J89: Maker should be able to log in, open Configuration > Debt Masters, search by master name, code or value and view the approved record and history. Maker should select Request Modification, amend the name, description, category or effective dates, or request deactivation; then enter the reason, save and submit. | K89: M01, M35 | N89: M01, M35 | O89: Must | P89: 1 - Foundation and Configuration | Q89: 1.5.1 | R89: Ready for Review
A90: 1 | B90: 1. General | C90: F01 | D90: Maintain master values | E90: F01-US06 | F90: Checker | G90: Existing | H90: As a Checker, I want to verify the proposed modification to Maintain master values, so that the operational and accounting impact is understood before approval. | I90: AC1. Given an authorised Checker is working with the approved existing record and its history, when the Maintain master values action is performed, then the system shall checker shall open the modification in Pending Verification and check old and new values, existing usage and any effect of deactivation on active records. AC2. Given an authorised Checker is working with the approved existing record and its history, when the Maintain master values action is performed, then the system shall the. AC3. Given an authorised Checker is working with the approved existing record and its history, when the Maintain master values action is performed, then the system shall checker shall return errors or verify and forward the revised request. AC4. Given the request is in Pending Verification, when the Checker acts, then the system shall enforce segregation of duties, show supporting evidence and relevant source/current values, and prevent the Maker from checking the same request. AC5. Given a validation fails, when Return is selected, then comments shall be mandatory and the request shall return to the Maker; when all checks pass, Verify and Forward shall place the checked version in the Approver queue and append the decision to R20. | J90: Checker should open the modification in Pending Verification and check old and new values, existing usage and any effect of deactivation on active records. The Checker should return errors or verify and forward the revised request. | K90: M01, M35 | N90: M01, M35 | O90: Must | P90: 1 - Foundation and Configuration | Q90: 1.5.1 | R90: Ready for Review
A91: 1 | B91: 1. General | C91: F01 | D91: Maintain master values | E91: F01-US07 | F91: Approver | G91: Existing | H91: As a Approver, I want to authorise or reject the checked modification to Maintain master values, so that only justified and authorised changes become effective. | I91: AC1. Given an authorised Approver is working with the approved existing record and its history, when the Maintain master values action is performed, then the system shall approver shall open the checked modification in Pending Approval, review the comparison, reason and effective date, and approve, return or reject it. The existing approved version remains unchanged until the revision becomes effective. AC2. Given a Checker-verified request, when the Approver reviews it, then configured authority, effective date, evidence and the checked version shall be displayed; the Maker or Checker of the request shall not approve it. AC3. Given the checked request is open in the Approver queue, when the Approver selects Approve, Return or Reject, then the system shall record the decision, comments, timestamp and authority in R20; only an approved effective version may update live records. | J91: Approver should open the checked modification in Pending Approval, review the comparison, reason and effective date, and approve, return or reject it. The existing approved version remains unchanged until the revision becomes effective. | K91: M01, M35 | N91: M01, M35 | O91: Must | P91: 1 - Foundation and Configuration | Q91: 1.5.1 | R91: Ready for Review
A92: 1 | B92: 1. General | C92: F01 | D92: Maintain master values | E92: F01-US08 | F92: System | G92: Existing | H92: As the system, I want to apply the approved modification to Maintain master values without overwriting history, so that current views are refreshed while actuals, postings and prior versions remain auditable. | I92: AC1. Given an authorised System is working with the approved existing record and its history, when the Maintain master values action is performed, then the system shall the. AC2. Given an authorised System is working with the approved existing record and its history, when the Maintain master values action is performed, then the system shall system shall refresh linked dropdowns and current descriptions after approval, prevent new use of inactive values and retain historical references without deleting them. AC3. Given an approved source event, when downstream processing runs or is retried, then the same source/version/idempotency key shall update each destination once only, with Success, Pending, Failed or Not Applicable recorded separately in R20 and reconciliation exceptions in R19. AC4. Given any destination update has failed, when the processing result is displayed or retried, then successful destinations shall remain traceable, the failure shall be visible and retryable, and the request shall not be incorrectly represented as fully completed. AC5. Given an approved revision or correction exists, when its effective date is reached and downstream processing runs, then future and eligible open items shall use the new effective version, while prior terms, settled transactions, posted journals and issued reports shall remain immutable and linked to the correction chain. | J92: The The The The The system should refresh linked dropdowns and current descriptions after approval, prevent new use of inactive values and retain historical references without deleting them. | K92: M01, M35 | N92: M01, M35 | O92: Must | P92: 1 - Foundation and Configuration | Q92: 1.5.1 | R92: Ready for Review
A93: 1 | B93: 1. General | C93: F02 | D93: Configure Maker, Checker and Approver routing | E93: F02-US01 | F93: Maker | G93: First-time | H93: As a Maker, I want to create, save and submit Configure Maker, Checker and Approver routing, so that the transaction can enter the controlled approval workflow. | I93: AC1. Given an authorised Maker is working with the new request, when the Configure Maker, Checker and Approver routing action is performed, then the system shall maker shall allow the user to log in, open Configuration > Workflow and Access and select Create Workflow Rule. AC2. Given an authorised Maker is working with the new request, when the Configure Maker, Checker and Approver routing action is performed, then the system shall maker shall select the debt function, action, organisation scope and authority range, then assign separate Maker, Checker and Approver roles or designations. AC3. Given an authorised Maker is working with the new request, when the Configure Maker, Checker and Approver routing action is performed, then the system shall maker shall enter effective dates, save the rule as a draft, test a sample route and submit it. AC4. Given the request is incomplete, when Save Draft is selected, then the system shall retain it as Draft, assign a request/version reference and make no change to approved balances, registers, books or the common GL. AC5. Given all mandatory validations pass, when Submit is selected, then the status shall become Submitted, the request shall enter the configured Checker queue and the submission shall be appended to R20. | J93: Maker should be able to log in, open Configuration > Workflow and Access and select Create Workflow Rule. Maker should select the debt function, action, organisation scope and authority range, then assign separate Maker, Checker and Approver roles or designations. Maker should enter effective dates, save the rule as a draft, test a sample route and submit it. | K93: C01, M01, M04, M10 | N93: C01, M01, M04, M10 | O93: Must | P93: 1 - Foundation and Configuration | Q93: 1.5.2 | R93: Ready for Review
A94: 1 | B94: 1. General | C94: F02 | D94: Configure Maker, Checker and Approver routing | E94: F02-US02 | F94: Checker | G94: First-time | H94: As a Checker, I want to verify a new Configure Maker, Checker and Approver routing request, so that only complete and valid requests proceed for authorisation. | I94: AC1. Given an authorised Checker is working with the new request, when the Configure Maker, Checker and Approver routing action is performed, then the system shall checker shall log in, open Pending Verification and check role eligibility, authority limits, segregation of duties and routing results. AC2. Given an authorised Checker is working with the new request, when the Configure Maker, Checker and Approver routing action is performed, then the system shall the. AC3. Given an authorised Checker is working with the new request, when the Configure Maker, Checker and Approver routing action is performed, then the system shall checker shall return errors with comments or select Verify and Forward. AC4. Given the request is in Pending Verification, when the Checker acts, then the system shall enforce segregation of duties, show supporting evidence and relevant source/current values, and prevent the Maker from checking the same request. AC5. Given a validation fails, when Return is selected, then comments shall be mandatory and the request shall return to the Maker; when all checks pass, Verify and Forward shall place the checked version in the Approver queue and append the decision to R20. | J94: Checker should log in, open Pending Verification and check role eligibility, authority limits, segregation of duties and routing results. The Checker should return errors with comments or select Verify and Forward. | K94: C01, M01, M04, M10 | N94: C01, M01, M04, M10 | O94: Must | P94: 1 - Foundation and Configuration | Q94: 1.5.2 | R94: Ready for Review
A95: 1 | B95: 1. General | C95: F02 | D95: Configure Maker, Checker and Approver routing | E95: F02-US03 | F95: Approver | G95: First-time | H95: As a Approver, I want to authorise a checked Configure Maker, Checker and Approver routing request, so that the approved version becomes authoritative within delegated powers. | I95: AC1. Given an authorised Approver is working with the new request, when the Configure Maker, Checker and Approver routing action is performed, then the system shall approver shall log in, open Pending Approval, review the checked record and supporting evidence, and approve, return or reject the request. Approval shall activate the workflow and access rule. AC2. Given a Checker-verified request, when the Approver reviews it, then configured authority, effective date, evidence and the checked version shall be displayed; the Maker or Checker of the request shall not approve it. AC3. Given the checked request is open in the Approver queue, when the Approver selects Approve, Return or Reject, then the system shall record the decision, comments, timestamp and authority in R20; only an approved effective version may update live records. | J95: Approver should log in, open Pending Approval, review the checked record and supporting evidence, and approve, return or reject the request. Approval should activate the workflow and access rule. | K95: C01, M01, M04, M10 | N95: C01, M01, M04, M10 | O95: Must | P95: 1 - Foundation and Configuration | Q95: 1.5.2 | R95: Ready for Review
A96: 1 | B96: 1. General | C96: F02 | D96: Configure Maker, Checker and Approver routing | E96: F02-US04 | F96: System | G96: First-time | H96: As the system, I want to apply an approved Configure Maker, Checker and Approver routing event to every affected record, so that registers, schedules, integrations, books, GL and reports remain consistent and traceable. | I96: AC1. Given an authorised System is working with the new request, when the Configure Maker, Checker and Approver routing action is performed, then the system shall the. AC2. Given an authorised System is working with the new request, when the Configure Maker, Checker and Approver routing action is performed, then the system shall system shall apply the rule to menus, permitted actions, work queues and new approval requests for the selected function. AC3. Given an approved source event, when downstream processing runs or is retried, then the same source/version/idempotency key shall update each destination once only, with Success, Pending, Failed or Not Applicable recorded separately in R20 and reconciliation exceptions in R19. AC4. Given any destination update has failed, when the processing result is displayed or retried, then successful destinations shall remain traceable, the failure shall be visible and retryable, and the request shall not be incorrectly represented as fully completed. | J96: The The The The The The system should apply the rule to menus, permitted actions, work queues and new approval requests for the selected function. | K96: C01, M01, M04, M10 | N96: C01, M01, M04, M10 | O96: Must | P96: 1 - Foundation and Configuration | Q96: 1.5.2 | R96: Ready for Review
... A100: 1 | B100: 1. General | C100: F02 | D100: Configure Maker, Checker and Approver routing | E100: F02-US08 | F100: System | G100: Existing | H100: As the system, I want to apply the approved modification to Configure Maker, Checker and Approver routing without overwriting history, so that current views are refreshed while actuals, postings and prior versions remain auditable. | I100: AC1. Given an authorised System is working with the approved existing record and its history, when the Configure Maker, Checker and Approver routing action is performed, then the system shall the. AC2. Given an authorised System is working with the approved existing record and its history, when the Configure Maker, Checker and Approver routing action is performed, then the system shall system shall update effective permissions and routing, reassign pending work only as authorised, and retain previous assignments and decisions. AC3. Given an approved source event, when downstream processing runs or is retried, then the same source/version/idempotency key shall update each destination once only, with Success, Pending, Failed or Not Applicable recorded separately in R20 and reconciliation exceptions in R19. AC4. Given any destination update has failed, when the processing result is displayed or retried, then successful destinations shall remain traceable, the failure shall be visible and retryable, and the request shall not be incorrectly represented as fully completed. AC5. Given an approved revision or correction exists, when its effective date is reached and downstream processing runs, then future and eligible open items shall use the new effective version, while prior terms, settled transactions, posted journals and issued reports shall remain immutable and linked to the correction chain. | J100: The The The The The system should update effective permissions and routing, reassign pending work only as authorised, and retain previous assignments and decisions. | K100: C01, M01, M04, M10 | N100: C01, M01, M04, M10 | O100: Must | P100: 1 - Foundation and Configuration | Q100: 1.5.2 | R100: Ready for Review
A101: 1 | B101: 1. General | C101: F03 | D101: Maintain exchange and interest rates | E101: F03-US01 | F101: Maker | G101: First-time | H101: As a Maker, I want to create, save and submit Maintain exchange and interest rates, so that the transaction can enter the controlled approval workflow. | I101: AC1. Given an authorised Maker is working with the new request, when the Maintain exchange and interest rates action is performed, then the system shall maker shall allow the user to log in, open Debt Management > Rates and select Add Rate. AC2. Given an authorised Maker is working with the new request, when the Maintain exchange and interest rates action is performed, then the system shall maker shall select Exchange Rate or Interest Rate, choose the currency pair or benchmark, and enter the rate, source, quotation basis and effective date. AC3. Given an authorised Maker is working with the new request, when the Maintain exchange and interest rates action is performed, then the system shall maker shall attach rate evidence, select Save Draft and submit the rate or import batch. AC4. Given the request is incomplete, when Save Draft is selected, then the system shall retain it as Draft, assign a request/version reference and make no change to approved balances, registers, books or the common GL. AC5. Given all mandatory validations pass, when Submit is selected, then the status shall become Submitted, the request shall enter the configured Checker queue and the submission shall be appended to R20. | J101: Maker should be able to log in, open Debt Management > Rates and select Add Rate. Maker should select Exchange Rate or Interest Rate, choose the currency pair or benchmark, and enter the rate, source, quotation basis and effective date. Maker should attach rate evidence, select Save Draft and submit the rate or import batch. | K101: C02, M04, M18, M21 | M101: 35 | N101: C02, M04, M18, M21 | O101: Must | P101: 1 - Foundation and Configuration | Q101: 1.5.3 | R101: Ready for Review
A102: 1 | B102: 1. General | C102: F03 | D102: Maintain exchange and interest rates | E102: F03-US02 | F102: Checker | G102: First-time | H102: As a Checker, I want to verify a new Maintain exchange and interest rates request, so that only complete and valid requests proceed for authorisation. | I102: AC1. Given an authorised Checker is working with the new request, when the Maintain exchange and interest rates action is performed, then the system shall checker shall log in, open Pending Verification and check source evidence, rate direction, effective date, duplicate values and unusual variations. AC2. Given an authorised Checker is working with the new request, when the Maintain exchange and interest rates action is performed, then the system shall the. AC3. Given an authorised Checker is working with the new request, when the Maintain exchange and interest rates action is performed, then the system shall checker shall return errors with comments or select Verify and Forward. AC4. Given the request is in Pending Verification, when the Checker acts, then the system shall enforce segregation of duties, show supporting evidence and relevant source/current values, and prevent the Maker from checking the same request. AC5. Given a validation fails, when Return is selected, then comments shall be mandatory and the request shall return to the Maker; when all checks pass, Verify and Forward shall place the checked version in the Approver queue and append the decision to R20. | J102: Checker should log in, open Pending Verification and check source evidence, rate direction, effective date, duplicate values and unusual variations. The Checker should return errors with comments or select Verify and Forward. | K102: C02, M04, M18, M21 | M102: 35 | N102: C02, M04, M18, M21 | O102: Must | P102: 1 - Foundation and Configuration | Q102: 1.5.3 | R102: Ready for Review
A103: 1 | B103: 1. General | C103: F03 | D103: Maintain exchange and interest rates | E103: F03-US03 | F103: Approver | G103: First-time | H103: As a Approver, I want to authorise a checked Maintain exchange and interest rates request, so that the approved version becomes authoritative within delegated powers. | I103: AC1. Given an authorised Approver is working with the new request, when the Maintain exchange and interest rates action is performed, then the system shall approver shall log in, open Pending Approval, review the checked record and supporting evidence, and approve, return or reject the request. Approval shall activate the checked dated rate. AC2. Given a Checker-verified request, when the Approver reviews it, then configured authority, effective date, evidence and the checked version shall be displayed; the Maker or Checker of the request shall not approve it. AC3. Given the checked request is open in the Approver queue, when the Approver selects Approve, Return or Reject, then the system shall record the decision, comments, timestamp and authority in R20; only an approved effective version may update live records. | J103: Approver should log in, open Pending Approval, review the checked record and supporting evidence, and approve, return or reject the request. Approval should activate the checked dated rate. | K103: C02, M04, M18, M21 | M103: 35 | N103: C02, M04, M18, M21 | O103: Must | P103: 1 - Foundation and Configuration | Q103: 1.5.3 | R103: Ready for Review
A104: 1 | B104: 1. General | C104: F03 | D104: Maintain exchange and interest rates | E104: F03-US04 | F104: System | G104: First-time | H104: As the system, I want to apply an approved Maintain exchange and interest rates event to every affected record, so that registers, schedules, integrations, books, GL and reports remain consistent and traceable. | I104: AC1. Given an authorised System is working with the new request, when the Maintain exchange and interest rates action is performed, then the system shall the. AC2. Given an authorised System is working with the new request, when the Maintain exchange and interest rates action is performed, then the system shall system shall use the approved rate in applicable new transactions, floating-rate calculations, forecasts and valuation requests. AC3. Given an approved source event, when downstream processing runs or is retried, then the same source/version/idempotency key shall update each destination once only, with Success, Pending, Failed or Not Applicable recorded separately in R20 and reconciliation exceptions in R19. AC4. Given any destination update has failed, when the processing result is displayed or retried, then successful destinations shall remain traceable, the failure shall be visible and retryable, and the request shall not be incorrectly represented as fully completed. | J104: The The The The The The system should use the approved rate in applicable new transactions, floating-rate calculations, forecasts and valuation requests. | K104: C02, M04, M18, M21 | M104: 35 | N104: C02, M04, M18, M21 | O104: Must | P104: 1 - Foundation and Configuration | Q104: 1.5.3 | R104: Ready for Review
A105: 1 | B105: 1. General | C105: F03 | D105: Maintain exchange and interest rates | E105: F03-US05 | F105: Maker | G105: Existing | H105: As a Maker, I want to find, review and request a controlled modification to Maintain exchange and interest rates, so that existing records can be corrected or amended with evidence and an effective date. | I105: AC1. Given an authorised Maker is working with the approved existing record and its history, when the Maintain exchange and interest rates action is performed, then the system shall maker shall allow the user to log in, open Debt Management > Rates, search by currency pair, benchmark or effective date and view the approved record and history. AC2. Given an authorised Maker is working with the approved existing record and its history, when the Maintain exchange and interest rates action is performed, then the system shall maker shall open the rate and select Request Correction, enter the revised value, reason and evidence, review affected records, save and submit. AC3. Given an approved record is modified, when the Maker submits the revision, then reason, effective date, amendment/evidence and before/after values shall be mandatory, and the existing approved version shall remain effective until approval and the configured effective date. | J105: Maker should be able to log in, open Debt Management > Rates, search by currency pair, benchmark or effective date and view the approved record and history. Maker should open the rate and select Request Correction, enter the revised value, reason and evidence, review affected records, save and submit. | K105: C02, M04, M18, M21 | M105: 35 | N105: C02, M04, M18, M21 | O105: Must | P105: 1 - Foundation and Configuration | Q105: 1.5.3 | R105: Ready for Review
A106: 1 | B106: 1. General | C106: F03 | D106: Maintain exchange and interest rates | E106: F03-US06 | F106: Checker | G106: Existing | H106: As a Checker, I want to verify the proposed modification to Maintain exchange and interest rates, so that the operational and accounting impact is understood before approval. | I106: AC1. Given an authorised Checker is working with the approved existing record and its history, when the Maintain exchange and interest rates action is performed, then the system shall checker shall open the modification in Pending Verification and check the corrected rate and its impact on schedules, pending transactions and valuation calculations. AC2. Given an authorised Checker is working with the approved existing record and its history, when the Maintain exchange and interest rates action is performed, then the system shall the. AC3. Given an authorised Checker is working with the approved existing record and its history, when the Maintain exchange and interest rates action is performed, then the system shall checker shall return errors or verify and forward the revised request. AC4. Given the request is in Pending Verification, when the Checker acts, then the system shall enforce segregation of duties, show supporting evidence and relevant source/current values, and prevent the Maker from checking the same request. AC5. Given a validation fails, when Return is selected, then comments shall be mandatory and the request shall return to the Maker; when all checks pass, Verify and Forward shall place the checked version in the Approver queue and append the decision to R20. | J106: Checker should open the modification in Pending Verification and check the corrected rate and its impact on schedules, pending transactions and valuation calculations. The Checker should return errors or verify and forward the revised request. | K106: C02, M04, M18, M21 | M106: 35 | N106: C02, M04, M18, M21 | O106: Must | P106: 1 - Foundation and Configuration | Q106: 1.5.3 | R106: Ready for Review
A107: 1 | B107: 1. General | C107: F03 | D107: Maintain exchange and interest rates | E107: F03-US07 | F107: Approver | G107: Existing | H107: As a Approver, I want to authorise or reject the checked modification to Maintain exchange and interest rates, so that only justified and authorised changes become effective. | I107: AC1. Given an authorised Approver is working with the approved existing record and its history, when the Maintain exchange and interest rates action is performed, then the system shall approver shall open the checked modification in Pending Approval, review the comparison, reason and effective date, and approve, return or reject it. The existing approved version remains unchanged until the revision becomes effective. AC2. Given a Checker-verified request, when the Approver reviews it, then configured authority, effective date, evidence and the checked version shall be displayed; the Maker or Checker of the request shall not approve it. AC3. Given the checked request is open in the Approver queue, when the Approver selects Approve, Return or Reject, then the system shall record the decision, comments, timestamp and authority in R20; only an approved effective version may update live records. | J107: Approver should open the checked modification in Pending Approval, review the comparison, reason and effective date, and approve, return or reject it. The existing approved version remains unchanged until the revision becomes effective. | K107: C02, M04, M18, M21 | M107: 35 | N107: C02, M04, M18, M21 | O107: Must | P107: 1 - Foundation and Configuration | Q107: 1.5.3 | R107: Ready for Review
A108: 1 | B108: 1. General | C108: F03 | D108: Maintain exchange and interest rates | E108: F03-US08 | F108: System | G108: Existing | H108: As the system, I want to apply the approved modification to Maintain exchange and interest rates without overwriting history, so that current views are refreshed while actuals, postings and prior versions remain auditable. | I108: AC1. Given an authorised System is working with the approved existing record and its history, when the Maintain exchange and interest rates action is performed, then the system shall the. AC2. Given an authorised System is working with the approved existing record and its history, when the Maintain exchange and interest rates action is performed, then the system shall system shall recalculate eligible open items and forecasts using the approved correction; posted or settled amounts retain their original rate and require adjustment where necessary. AC3. Given an approved source event, when downstream processing runs or is retried, then the same source/version/idempotency key shall update each destination once only, with Success, Pending, Failed or Not Applicable recorded separately in R20 and reconciliation exceptions in R19. AC4. Given any destination update has failed, when the processing result is displayed or retried, then successful destinations shall remain traceable, the failure shall be visible and retryable, and the request shall not be incorrectly represented as fully completed. AC5. Given an approved revision or correction exists, when its effective date is reached and downstream processing runs, then future and eligible open items shall use the new effective version, while prior terms, settled transactions, posted journals and issued reports shall remain immutable and linked to the correction chain. | J108: The The The The The system should recalculate eligible open items and forecasts using the approved correction; posted or settled amounts retain their original rate and require adjustment where necessary. | K108: C02, M04, M18, M21 | M108: 35 | N108: C02, M04, M18, M21 | O108: Must | P108: 1 - Foundation and Configuration | Q108: 1.5.3 | R108: Ready for Review
A109: 1 | B109: 1. General | C109: F04 | D109: Configure CoA mapping and accounting rules | E109: F04-US01 | F109: Maker | G109: First-time | H109: As a Maker, I want to create, save and submit Configure CoA mapping and accounting rules, so that the transaction can enter the controlled approval workflow. | I109: AC1. Given an authorised Maker is working with the new request, when the Configure CoA mapping and accounting rules action is performed, then the system shall maker shall allow the user to log in, open Configuration > Debt Accounting Rules and select Create Posting Rule. AC2. Given an authorised Maker is working with the new request, when the Configure CoA mapping and accounting rules action is performed, then the system shall maker shall select the accounting event, instrument type, component and accounting basis/book, then select existing debit and credit CoA codes and required dimensions. AC3. Given an authorised Maker is working with the new request, when the Configure CoA mapping and accounting rules action is performed, then the system shall maker shall enter effective dates, preview a sample entry, select Save Draft and submit the rule. AC4. Given the request is incomplete, when Save Draft is selected, then the system shall retain it as Draft, assign a request/version reference and make no change to approved balances, registers, books or the common GL. AC5. Given all mandatory validations pass, when Submit is selected, then the status shall become Submitted, the request shall enter the configured Checker queue and the submission shall be appended to R20. | J109: Maker should be able to log in, open Configuration > Debt Accounting Rules and select Create Posting Rule. Maker should select the accounting event, instrument type, component and accounting basis/book, then select existing debit and credit CoA codes and required dimensions. Maker should enter effective dates, preview a sample entry, select Save Draft and submit the rule. | K109: C05, M07, M12, M23, M32, M33 | M109: 36 | N109: C05, M07, M12, M23, M32, M33 | O109: Must | P109: 1 - Foundation and Configuration | Q109: 1.5.4 | R109: Ready for Review
A110: 1 | B110: 1. General | C110: F04 | D110: Configure CoA mapping and accounting rules | E110: F04-US02 | F110: Checker | G110: First-time | H110: As a Checker, I want to verify a new Configure CoA mapping and accounting rules request, so that only complete and valid requests proceed for authorisation. | I110: AC1. Given an authorised Checker is working with the new request, when the Configure CoA mapping and accounting rules action is performed, then the system shall checker shall log in, open Pending Verification and check active CoA codes, balanced entries, dimensions, rule conflicts and cash/accrual/hybrid treatment. AC2. Given an authorised Checker is working with the new request, when the Configure CoA mapping and accounting rules action is performed, then the system shall the. AC3. Given an authorised Checker is working with the new request, when the Configure CoA mapping and accounting rules action is performed, then the system shall checker shall return errors with comments or select Verify and Forward. AC4. Given the request is in Pending Verification, when the Checker acts, then the system shall enforce segregation of duties, show supporting evidence and relevant source/current values, and prevent the Maker from checking the same request. AC5. Given a validation fails, when Return is selected, then comments shall be mandatory and the request shall return to the Maker; when all checks pass, Verify and Forward shall place the checked version in the Approver queue and append the decision to R20. | J110: Checker should log in, open Pending Verification and check active CoA codes, balanced entries, dimensions, rule conflicts and cash/accrual/hybrid treatment. The Checker should return errors with comments or select Verify and Forward. | K110: C05, M07, M12, M23, M32, M33 | M110: 36 | N110: C05, M07, M12, M23, M32, M33 | O110: Must | P110: 1 - Foundation and Configuration | Q110: 1.5.4 | R110: Ready for Review
A111: 1 | B111: 1. General | C111: F04 | D111: Configure CoA mapping and accounting rules | E111: F04-US03 | F111: Approver | G111: First-time | H111: As a Approver, I want to authorise a checked Configure CoA mapping and accounting rules request, so that the approved version becomes authoritative within delegated powers. | I111: AC1. Given an authorised Approver is working with the new request, when the Configure CoA mapping and accounting rules action is performed, then the system shall approver shall log in, open Pending Approval, review the checked record and supporting evidence, and approve, return or reject the request. Approval shall activate the tested posting rule. AC2. Given a Checker-verified request, when the Approver reviews it, then configured authority, effective date, evidence and the checked version shall be displayed; the Maker or Checker of the request shall not approve it. AC3. Given the checked request is open in the Approver queue, when the Approver selects Approve, Return or Reject, then the system shall record the decision, comments, timestamp and authority in R20; only an approved effective version may update live records. | J111: Approver should log in, open Pending Approval, review the checked record and supporting evidence, and approve, return or reject the request. Approval should activate the tested posting rule. | K111: C05, M07, M12, M23, M32, M33 | M111: 36 | N111: C05, M07, M12, M23, M32, M33 | O111: Must | P111: 1 - Foundation and Configuration | Q111: 1.5.4 | R111: Ready for Review
A112: 1 | B112: 1. General | C112: F04 | D112: Configure CoA mapping and accounting rules | E112: F04-US04 | F112: System | G112: First-time | H112: As the system, I want to apply an approved Configure CoA mapping and accounting rules event to every affected record, so that registers, schedules, integrations, books, GL and reports remain consistent and traceable. | I112: AC1. Given an authorised System is working with the new request, when the Configure CoA mapping and accounting rules action is performed, then the system shall the. AC2. Given an authorised System is working with the new request, when the Configure CoA mapping and accounting rules action is performed, then the system shall system shall apply the approved rule to eligible accounting previews and new postings, retaining the rule version on each entry. AC3. Given an approved source event, when downstream processing runs or is retried, then the same source/version/idempotency key shall update each destination once only, with Success, Pending, Failed or Not Applicable recorded separately in R20 and reconciliation exceptions in R19. AC4. Given any destination update has failed, when the processing result is displayed or retried, then successful destinations shall remain traceable, the failure shall be visible and retryable, and the request shall not be incorrectly represented as fully completed. | J112: The The The The The The system should apply the approved rule to eligible accounting previews and new postings, retaining the rule version on each entry. | K112: C05, M07, M12, M23, M32, M33 | M112: 36 | N112: C05, M07, M12, M23, M32, M33 | O112: Must | P112: 1 - Foundation and Configuration | Q112: 1.5.4 | R112: Ready for Review
... A116: 1 | B116: 1. General | C116: F04 | D116: Configure CoA mapping and accounting rules | E116: F04-US08 | F116: System | G116: Existing | H116: As the system, I want to apply the approved modification to Configure CoA mapping and accounting rules without overwriting history, so that current views are refreshed while actuals, postings and prior versions remain auditable. | I116: AC1. Given an authorised System is working with the approved existing record and its history, when the Configure CoA mapping and accounting rules action is performed, then the system shall the. AC2. Given an authorised System is working with the approved existing record and its history, when the Configure CoA mapping and accounting rules action is performed, then the system shall system shall refresh eligible unposted entries and future postings; existing GL entries must not be overwritten and shall be corrected through approved adjustments. AC3. Given an approved source event, when downstream processing runs or is retried, then the same source/version/idempotency key shall update each destination once only, with Success, Pending, Failed or Not Applicable recorded separately in R20 and reconciliation exceptions in R19. AC4. Given any destination update has failed, when the processing result is displayed or retried, then successful destinations shall remain traceable, the failure shall be visible and retryable, and the request shall not be incorrectly represented as fully completed. AC5. Given an approved revision or correction exists, when its effective date is reached and downstream processing runs, then future and eligible open items shall use the new effective version, while prior terms, settled transactions, posted journals and issued reports shall remain immutable and linked to the correction chain. | J116: The The The The The system should refresh eligible unposted entries and future postings; existing GL entries must not be overwritten and should be corrected through approved adjustments. | K116: C05, M07, M12, M23, M32, M33 | M116: 36 | N116: C05, M07, M12, M23, M32, M33 | O116: Must | P116: 1 - Foundation and Configuration | Q116: 1.5.4 | R116: Ready for Review
A117: 6 | B117: 6. Accounting by instrument type | C117: AC01 | D117: Accounting masters and configuration | E117: AC01-US01 | F117: Maker | G117: First-time | H117: As a Maker, I want to create, save and submit Accounting masters and configuration, so that the transaction can enter the controlled approval workflow. | I117: AC1. Given an authorised Maker is working with the new request, when the Accounting masters and configuration action is performed, then the system shall maker shall allow the user to log in, open Configuration > Debt Accounting, and select Create Register/Postings Mapping. AC2. Given an authorised Maker is working with the new request, when the Accounting masters and configuration action is performed, then the system shall maker shall select the instrument type/subtype, event, register, accounting basis/book and existing CoA/HoA codes, then enter the source trigger, field mappings, effective dates and reversal rule. AC3. Given an authorised Maker is working with the new request, when the Accounting masters and configuration action is performed, then the system shall maker shall run sample-event and reversal tests, review the proposed register and journal outputs, attach the policy approval, select Save Draft and submit. AC4. Given the request is incomplete, when Save Draft is selected, then the system shall retain it as Draft, assign a request/version reference and make no change to approved balances, registers, books or the common GL. AC5. Given all mandatory validations pass, when Submit is selected, then the status shall become Submitted, the request shall enter the configured Checker queue and the submission shall be appended to R20. | J117: Maker should be able to log in, open Configuration > Debt Accounting, and select Create Register/Postings Mapping. Maker should select the instrument type/subtype, event, register, accounting basis/book and existing CoA/HoA codes, then enter the source trigger, field mappings, effective dates and reversal rule. Maker should run sample-event and reversal tests, review the proposed register and journal outputs, attach the policy approval, select Save Draft and submit. | K117: C05, C06 | L117: R01, R06, R07, R18, R19, R20 | M117: 36 | N117: C05, C06, R01, R06, R07, R18, R19, R20 | O117: Must | P117: 1 - Foundation and Configuration | Q117: 6.1.1 | R117: Ready for Review
A118: 6 | B118: 6. Accounting by instrument type | C118: AC01 | D118: Accounting masters and configuration | E118: AC01-US02 | F118: Checker | G118: First-time | H118: As a Checker, I want to verify a new Accounting masters and configuration request, so that only complete and valid requests proceed for authorisation. | I118: AC1. Given an authorised Checker is working with the new request, when the Accounting masters and configuration action is performed, then the system shall checker shall log in, open Pending Verification, and check source ownership, trigger timing, field completeness, balanced posting rules, period controls and test results. AC2. Given an authorised Checker is working with the new request, when the Accounting masters and configuration action is performed, then the system shall the. AC3. Given an authorised Checker is working with the new request, when the Accounting masters and configuration action is performed, then the system shall checker shall return errors or verify and forward. AC4. Given the request is in Pending Verification, when the Checker acts, then the system shall enforce segregation of duties, show supporting evidence and relevant source/current values, and prevent the Maker from checking the same request. AC5. Given a validation fails, when Return is selected, then comments shall be mandatory and the request shall return to the Maker; when all checks pass, Verify and Forward shall place the checked version in the Approver queue and append the decision to R20. | J118: Checker should log in, open Pending Verification, and check source ownership, trigger timing, field completeness, balanced posting rules, period controls and test results. The Checker should return errors or verify and forward. | K118: C05, C06 | L118: R01, R06, R07, R18, R19, R20 | M118: 36 | N118: C05, C06, R01, R06, R07, R18, R19, R20 | O118: Must | P118: 1 - Foundation and Configuration | Q118: 6.1.1 | R118: Ready for Review
A119: 6 | B119: 6. Accounting by instrument type | C119: AC01 | D119: Accounting masters and configuration | E119: AC01-US03 | F119: Approver | G119: First-time | H119: As a Approver, I want to authorise a checked Accounting masters and configuration request, so that the approved version becomes authoritative within delegated powers. | I119: AC1. Given an authorised Approver is working with the new request, when the Accounting masters and configuration action is performed, then the system shall approver shall log in, open Pending Approval, review the checked mapping and policy evidence, and approve, return or reject it. AC2. Given a Checker-verified request, when the Approver reviews it, then configured authority, effective date, evidence and the checked version shall be displayed; the Maker or Checker of the request shall not approve it. AC3. Given the checked request is open in the Approver queue, when the Approver selects Approve, Return or Reject, then the system shall record the decision, comments, timestamp and authority in R20; only an approved effective version may update live records. | J119: Approver should log in, open Pending Approval, review the checked mapping and policy evidence, and approve, return or reject it. | K119: C05, C06 | L119: R01, R06, R07, R18, R19, R20 | M119: 36 | N119: C05, C06, R01, R06, R07, R18, R19, R20 | O119: Must | P119: 1 - Foundation and Configuration | Q119: 6.1.1 | R119: Ready for Review
A120: 6 | B120: 6. Accounting by instrument type | C120: AC01 | D120: Accounting masters and configuration | E120: AC01-US04 | F120: System | G120: First-time | H120: As the system, I want to apply an approved Accounting masters and configuration event to every affected record, so that registers, schedules, integrations, books, GL and reports remain consistent and traceable. | I120: AC1. Given an authorised System is working with the new request, when the Accounting masters and configuration action is performed, then the system shall the. AC2. Given an authorised System is working with the new request, when the Accounting masters and configuration action is performed, then the system shall system shall activate the approved C05/C06 version from its effective date and update event dropdowns, register mappings, validation rules and posting previews. R20 shall retain the approval. Creating a rule must not itself create actual transactions or GL entries. AC3. Given an approved source event, when downstream processing runs or is retried, then the same source/version/idempotency key shall update each destination once only, with Success, Pending, Failed or Not Applicable recorded separately in R20 and reconciliation exceptions in R19. AC4. Given any destination update has failed, when the processing result is displayed or retried, then successful destinations shall remain traceable, the failure shall be visible and retryable, and the request shall not be incorrectly represented as fully completed. | J120: The The The The The The system should activate the approved C05/C06 version from its effective date and update event dropdowns, register mappings, validation rules and posting previews. R20 should retain the approval. Creating a rule must not itself create actual transactions or GL entries. | K120: C05, C06 | L120: R01, R06, R07, R18, R19, R20 | M120: 36 | N120: C05, C06, R01, R06, R07, R18, R19, R20 | O120: Must | P120: 1 - Foundation and Configuration | Q120: 6.1.1 | R120: Ready for Review
A121: 6 | B121: 6. Accounting by instrument type | C121: AC01 | D121: Accounting masters and configuration | E121: AC01-US05 | F121: Maker | G121: Existing | H121: As a Maker, I want to find, review and request a controlled modification to Accounting masters and configuration, so that existing records can be corrected or amended with evidence and an effective date. | I121: AC1. Given an authorised Maker is working with the approved existing record and its history, when the Accounting masters and configuration action is performed, then the system shall maker shall allow the user to log in, open Configuration > Debt Accounting, search by rule ID, instrument subtype or event, and view the approved mapping and history. AC2. Given an authorised Maker is working with the approved existing record and its history, when the Accounting masters and configuration action is performed, then the system shall maker shall select Modify Mapping, change the required fields, enter the reason and effective date, run impact and reversal tests, save the new version and submit. AC3. Given an approved record is modified, when the Maker submits the revision, then reason, effective date, amendment/evidence and before/after values shall be mandatory, and the existing approved version shall remain effective until approval and the configured effective date. | J121: Maker should be able to log in, open Configuration > Debt Accounting, search by rule ID, instrument subtype or event, and view the approved mapping and history. Maker should select Modify Mapping, change the required fields, enter the reason and effective date, run impact and reversal tests, save the new version and submit. | K121: C05, C06 | L121: R01, R06, R07, R18, R19, R20 | M121: 36 | N121: C05, C06, R01, R06, R07, R18, R19, R20 | O121: Must | P121: 1 - Foundation and Configuration | Q121: 6.1.1 | R121: Ready for Review
A122: 6 | B122: 6. Accounting by instrument type | C122: AC01 | D122: Accounting masters and configuration | E122: AC01-US06 | F122: Checker | G122: Existing | H122: As a Checker, I want to verify the proposed modification to Accounting masters and configuration, so that the operational and accounting impact is understood before approval. | I122: AC1. Given an authorised Checker is working with the approved existing record and its history, when the Accounting masters and configuration action is performed, then the system shall checker shall compare old and new mappings, check pending-event impacts and identify any posted events needing a separately approved correction. AC2. Given an authorised Checker is working with the approved existing record and its history, when the Accounting masters and configuration action is performed, then the system shall the. AC3. Given an authorised Checker is working with the approved existing record and its history, when the Accounting masters and configuration action is performed, then the system shall checker shall return errors or verify and forward. AC4. Given the request is in Pending Verification, when the Checker acts, then the system shall enforce segregation of duties, show supporting evidence and relevant source/current values, and prevent the Maker from checking the same request. AC5. Given a validation fails, when Return is selected, then comments shall be mandatory and the request shall return to the Maker; when all checks pass, Verify and Forward shall place the checked version in the Approver queue and append the decision to R20. | J122: Checker should compare old and new mappings, check pending-event impacts and identify any posted events needing a separately approved correction. The Checker should return errors or verify and forward. | K122: C05, C06 | L122: R01, R06, R07, R18, R19, R20 | M122: 36 | N122: C05, C06, R01, R06, R07, R18, R19, R20 | O122: Must | P122: 1 - Foundation and Configuration | Q122: 6.1.1 | R122: Ready for Review
A123: 6 | B123: 6. Accounting by instrument type | C123: AC01 | D123: Accounting masters and configuration | E123: AC01-US07 | F123: Approver | G123: Existing | H123: As a Approver, I want to authorise or reject the checked modification to Accounting masters and configuration, so that only justified and authorised changes become effective. | I123: AC1. Given an authorised Approver is working with the approved existing record and its history, when the Accounting masters and configuration action is performed, then the system shall approver shall review the checked change, policy evidence and impact list, then approve, return or reject it. The old version remains effective until the approved replacement date. AC2. Given a Checker-verified request, when the Approver reviews it, then configured authority, effective date, evidence and the checked version shall be displayed; the Maker or Checker of the request shall not approve it. AC3. Given the checked request is open in the Approver queue, when the Approver selects Approve, Return or Reject, then the system shall record the decision, comments, timestamp and authority in R20; only an approved effective version may update live records. | J123: Approver should review the checked change, policy evidence and impact list, then approve, return or reject it. The old version remains effective until the approved replacement date. | K123: C05, C06 | L123: R01, R06, R07, R18, R19, R20 | M123: 36 | N123: C05, C06, R01, R06, R07, R18, R19, R20 | O123: Must | P123: 1 - Foundation and Configuration | Q123: 6.1.1 | R123: Ready for Review
A124: 6 | B124: 6. Accounting by instrument type | C124: AC01 | D124: Accounting masters and configuration | E124: AC01-US08 | F124: System | G124: Existing | H124: As the system, I want to apply the approved modification to Accounting masters and configuration without overwriting history, so that current views are refreshed while actuals, postings and prior versions remain auditable. | I124: AC1. Given an authorised System is working with the approved existing record and its history, when the Accounting masters and configuration action is performed, then the system shall the. AC2. Given an authorised System is working with the approved existing record and its history, when the Accounting masters and configuration action is performed, then the system shall system shall update the effective configuration, dropdowns, register mappings and future posting previews, retain both versions in R20, and flag pending requests needing revalidation. It must not silently recalculate or repost approved history. AC3. Given an authorised System is working with the approved existing record and its history, when the Accounting masters and configuration action is performed, then the system shall system shall show draft and checked requests in workflow views only. They shall not change approved actuals, subsidiary-book balances or the common GL. AC4. Given an authorised System is working with the approved existing record and its history, when the Accounting masters and configuration action is performed, then the system shall system shall populate an approved non-financial event, such as an allocation or schedule, when approval becomes effective. Agreement approval alone shall not be treated as cash received, cash paid or drawn principal; any policy-required commitment recognition is a separate configured event. AC5. Given an authorised System is working with the approved existing record and its history, when the Accounting masters and configuration action is performed, then the system shall system shall populate actual receipt/payment registers only from an approved event with validated bank, Treasury, settlement or direct-payment evidence. Approval of a Claim Request alone shall not mark the claim as paid. AC6. Given an authorised System is working with the approved existing record and its history, when the Accounting masters and configuration action is performed, then the system shall system shall populate R18 with the accounting event and draft journal. Only approved, eligible financial events shall be released for posting. It shall update the relevant books and common GL after successful acknowledgement, then update R18 and the R19 reconciliation status. | J124: The The The The The system should update the effective configuration, dropdowns, register mappings and future posting previews, retain both versions in R20, and flag pending requests needing revalidation. It must not silently recalculate or repost approved history. The system should show draft and checked requests in workflow views only. They should not change approved actuals, subsidiary-book balances or the common GL. The system should populate an approved non-financial event, such as an allocation or schedule, when approval becomes effective. Agreement approval alone should not be treated as cash received, cash paid or drawn principal; any policy-required commitment recognition is a separate configured event. The system should populate actual receipt/payment registers only from an approved event with validated bank, Treasury, settlement or direct-payment evidence. Approval of a Claim Request alone should not mark the claim as paid. The system should populate R18 with the accounting event and draft journal. Only approved, eligible financial events should be released for posting. It should update the relevant books and common GL after successful acknowledgement, then update R18 and the R19 reconciliation status. The system should record every creation, amendment, approval and correction in R20. All financial rows in the subtype matrices also require R18 and R19, even where those codes are not repeated in the row. Operational-only rows require no journal unless a separate approved recognition rule applies. The system should separate cash, accrual and hybrid outputs. Cash books use receipt/payment recognition; accrual books may include receivables, payables, amortisation, impairment and valuation. Hybrid processing must specify the basis for each component, and reports must not add alternative-basis balances together. The system should use one posting owner per source event. If the expenditure, Treasury or another module already posted the event, Debt Management should link that voucher and update its registers rather than create a duplicate journal. The system should keep contractual principal, face value, cash proceeds, accrued components and accounting carrying amount as separate fields. A valuation, discount or impairment adjustment must not silently alter contractual principal. The system should keep borrowing liabilities, lending receivables, grants and guarantee exposures separately identifiable. A guarantee is not the underlying government borrowing; however, applicable accrual policy may require a separate financial-guarantee liability before invocation. | K124: C05, C06 | L124: R01, R06, R07, R18, R19, R20 | M124: 36 | N124: C05, C06, R01, R06, R07, R18, R19, R20 | O124: Must | P124: 1 - Foundation and Configuration | Q124: 6.1.1 | R124: Ready for Review
A125: 6 | B125: 6. Accounting by instrument type | C125: AC02 | D125: First-time opening balances and migrated instruments | E125: AC02-US01 | F125: Maker | G125: First-time | H125: As a Maker, I want to create, save and submit First-time opening balances and migrated instruments, so that the transaction can enter the controlled approval workflow. | I125: AC1. Given an authorised Maker is working with the new request, when the First-time opening balances and migrated instruments action is performed, then the system shall maker shall allow the user to log in, open Debt Management > Accounting > Opening Balances, and select Create Accounting Request. AC2. Given an authorised Maker is working with the new request, when the First-time opening balances and migrated instruments action is performed, then the system shall maker shall select the cut-off date, entity and basis/book; import instruments with original IDs, principal, accrued components, allowances, grant balances and guarantee exposure, and map existing Project/Program and CoA IDs. AC3. Given an authorised Maker is working with the new request, when the First-time opening balances and migrated instruments action is performed, then the system shall the. AC4. Given an authorised Maker is working with the new request, when the First-time opening balances and migrated instruments action is performed, then the system shall maker shall review the event date, amount, currency, book, CoA/HoA, existing Project/Program link and supporting evidence, select Save Draft, and submit for checking. AC5. Given the request is incomplete, when Save Draft is selected, then the system shall retain it as Draft, assign a request/version reference and make no change to approved balances, registers, books or the common GL. AC6. Given all mandatory validations pass, when Submit is selected, then the status shall become Submitted, the request shall enter the configured Checker queue and the submission shall be appended to R20. | J125: Maker should be able to log in, open Debt Management > Accounting > Opening Balances, and select Create Accounting Request. Maker should select the cut-off date, entity and basis/book; import instruments with original IDs, principal, accrued components, allowances, grant balances and guarantee exposure, and map existing Project/Program and CoA IDs. The Maker should review the event date, amount, currency, book, CoA/HoA, existing Project/Program link and supporting evidence, select Save Draft, and submit for checking. | K125: C05 | L125: R01, R17, R18, R20 | N125: C05, R01, R17, R18, R20 | O125: Must | P125: 1 - Foundation and Configuration | Q125: 6.1.5 | R125: Ready for Review
A126: 6 | B126: 6. Accounting by instrument type | C126: AC02 | D126: First-time opening balances and migrated instruments | E126: AC02-US02 | F126: Checker | G126: First-time | H126: As a Checker, I want to verify a new First-time opening balances and migrated instruments request, so that only complete and valid requests proceed for authorisation. | I126: AC1. Given an authorised Checker is working with the new request, when the First-time opening balances and migrated instruments action is performed, then the system shall checker shall log in, open Pending Verification, and check source schedules, creditor/borrower confirmations, opening principal versus accrued components, duplicate IDs and reconciliation to the existing trial balance. AC2. Given an authorised Checker is working with the new request, when the First-time opening balances and migrated instruments action is performed, then the system shall the. AC3. Given an authorised Checker is working with the new request, when the First-time opening balances and migrated instruments action is performed, then the system shall checker shall return errors with comments or verify and forward the request. AC4. Given the request is in Pending Verification, when the Checker acts, then the system shall enforce segregation of duties, show supporting evidence and relevant source/current values, and prevent the Maker from checking the same request. AC5. Given a validation fails, when Return is selected, then comments shall be mandatory and the request shall return to the Maker; when all checks pass, Verify and Forward shall place the checked version in the Approver queue and append the decision to R20. | J126: Checker should log in, open Pending Verification, and check source schedules, creditor/borrower confirmations, opening principal versus accrued components, duplicate IDs and reconciliation to the existing trial balance. The Checker should return errors with comments or verify and forward the request. | K126: C05 | L126: R01, R17, R18, R20 | N126: C05, R01, R17, R18, R20 | O126: Must | P126: 1 - Foundation and Configuration | Q126: 6.1.5 | R126: Ready for Review
A127: 6 | B127: 6. Accounting by instrument type | C127: AC02 | D127: First-time opening balances and migrated instruments | E127: AC02-US03 | F127: Approver | G127: First-time | H127: As a Approver, I want to authorise a checked First-time opening balances and migrated instruments request, so that the approved version becomes authoritative within delegated powers. | I127: AC1. Given an authorised Approver is working with the new request, when the First-time opening balances and migrated instruments action is performed, then the system shall approver shall log in, open Pending Approval, review the checked request and posting preview, and approve, return or reject it. Approval shall release only the validated event version. AC2. Given a Checker-verified request, when the Approver reviews it, then configured authority, effective date, evidence and the checked version shall be displayed; the Maker or Checker of the request shall not approve it. AC3. Given the checked request is open in the Approver queue, when the Approver selects Approve, Return or Reject, then the system shall record the decision, comments, timestamp and authority in R20; only an approved effective version may update live records. | J127: Approver should log in, open Pending Approval, review the checked request and posting preview, and approve, return or reject it. Approval should release only the validated event version. | K127: C05 | L127: R01, R17, R18, R20 | N127: C05, R01, R17, R18, R20 | O127: Must | P127: 1 - Foundation and Configuration | Q127: 6.1.5 | R127: Ready for Review
A128: 6 | B128: 6. Accounting by instrument type | C128: AC02 | D128: First-time opening balances and migrated instruments | E128: AC02-US04 | F128: System | G128: First-time | H128: As the system, I want to apply an approved First-time opening balances and migrated instruments event to every affected record, so that registers, schedules, integrations, books, GL and reports remain consistent and traceable. | I128: AC1. Given an authorised System is working with the new request, when the First-time opening balances and migrated instruments action is performed, then the system shall the. AC2. Given an authorised System is working with the new request, when the First-time opening balances and migrated instruments action is performed, then the system shall system shall derive the register updates and draft entries from the event matrix and approved C05 rules. AC3. Given an authorised System is working with the new request, when the First-time opening balances and migrated instruments action is performed, then the system shall system shall update the applicable R01-R17 opening positions, B02-B05 opening views and approved schedules, with GL links or one authorised opening journal only where required. It shall retain the acknowledged voucher and destination-wise update status in R18-R20; unacknowledged entries remain unposted. AC4. Given an approved source event, when downstream processing runs or is retried, then the same source/version/idempotency key shall update each destination once only, with Success, Pending, Failed or Not Applicable recorded separately in R20 and reconciliation exceptions in R19. AC5. Given any destination update has failed, when the processing result is displayed or retried, then successful destinations shall remain traceable, the failure shall be visible and retryable, and the request shall not be incorrectly represented as fully completed. | J128: The The system should derive the register updates and draft entries from the event matrix and approved C05 rules. The The The The system should update the applicable R01-R17 opening positions, B02-B05 opening views and approved schedules, with GL links or one authorised opening journal only where required. It should retain the acknowledged voucher and destination-wise update status in R18-R20; unacknowledged entries remain unposted. | K128: C05 | L128: R01, R17, R18, R20 | N128: C05, R01, R17, R18, R20 | O128: Must | P128: 1 - Foundation and Configuration | Q128: 6.1.5 | R128: Ready for Review
A129: 6 | B129: 6. Accounting by instrument type | C129: AC02 | D129: First-time opening balances and migrated instruments | E129: AC02-US05 | F129: Maker | G129: Existing | H129: As a Maker, I want to find, review and request a controlled modification to First-time opening balances and migrated instruments, so that existing records can be corrected or amended with evidence and an effective date. | I129: AC1. Given an authorised Maker is working with the approved existing record and its history, when the First-time opening balances and migrated instruments action is performed, then the system shall maker shall allow the user to log in, open Opening Balances, search by instrument ID, event ID or voucher reference, and view the registers, books, common GL link and approval history. AC2. Given an authorised Maker is working with the approved existing record and its history, when the First-time opening balances and migrated instruments action is performed, then the system shall maker shall select the approved opening package and create an opening-balance correction for the affected instrument and component, without replacing later actual transactions. AC3. Given an authorised Maker is working with the approved existing record and its history, when the First-time opening balances and migrated instruments action is performed, then the system shall the. AC4. Given an authorised Maker is working with the approved existing record and its history, when the First-time opening balances and migrated instruments action is performed, then the system shall maker shall enter the reason and effective date, attach evidence, save the linked amendment or correction request, and submit it. AC5. Given an approved record is modified, when the Maker submits the revision, then reason, effective date, amendment/evidence and before/after values shall be mandatory, and the existing approved version shall remain effective until approval and the configured effective date. | J129: Maker should be able to log in, open Opening Balances, search by instrument ID, event ID or voucher reference, and view the registers, books, common GL link and approval history. Maker should select the approved opening package and create an opening-balance correction for the affected instrument and component, without replacing later actual transactions. The Maker should enter the reason and effective date, attach evidence, save the linked amendment or correction request, and submit it. | K129: C05 | L129: R01, R17, R18, R20 | N129: C05, R01, R17, R18, R20 | O129: Must | P129: 1 - Foundation and Configuration | Q129: 6.1.5 | R129: Ready for Review
A130: 6 | B130: 6. Accounting by instrument type | C130: AC02 | D130: First-time opening balances and migrated instruments | E130: AC02-US06 | F130: Checker | G130: Existing | H130: As a Checker, I want to verify the proposed modification to First-time opening balances and migrated instruments, so that the operational and accounting impact is understood before approval. | I130: AC1. Given an authorised Checker is working with the approved existing record and its history, when the First-time opening balances and migrated instruments action is performed, then the system shall checker shall compare the original and proposed records and check the cut-off, subsequent movements, source evidence and the exact difference against both the opening register and the common GL. Posted amounts must be corrected through linked reversal or adjustment entries, not overwritten. AC2. Given the request is in Pending Verification, when the Checker acts, then the system shall enforce segregation of duties, show supporting evidence and relevant source/current values, and prevent the Maker from checking the same request. AC3. Given a validation fails, when Return is selected, then comments shall be mandatory and the request shall return to the Maker; when all checks pass, Verify and Forward shall place the checked version in the Approver queue and append the decision to R20. | J130: Checker should compare the original and proposed records and check the cut-off, subsequent movements, source evidence and the exact difference against both the opening register and the common GL. Posted amounts must be corrected through linked reversal or adjustment entries, not overwritten. | K130: C05 | L130: R01, R17, R18, R20 | N130: C05, R01, R17, R18, R20 | O130: Must | P130: 1 - Foundation and Configuration | Q130: 6.1.5 | R130: Ready for Review
A131: 6 | B131: 6. Accounting by instrument type | C131: AC02 | D131: First-time opening balances and migrated instruments | E131: AC02-US07 | F131: Approver | G131: Existing | H131: As a Approver, I want to authorise or reject the checked modification to First-time opening balances and migrated instruments, so that only justified and authorised changes become effective. | I131: AC1. Given an authorised Approver is working with the approved existing record and its history, when the First-time opening balances and migrated instruments action is performed, then the system shall approver shall review the checked change and its impact, then approve, return or reject it. A returned or rejected request shall leave the current approved record unchanged. AC2. Given a Checker-verified request, when the Approver reviews it, then configured authority, effective date, evidence and the checked version shall be displayed; the Maker or Checker of the request shall not approve it. AC3. Given the checked request is open in the Approver queue, when the Approver selects Approve, Return or Reject, then the system shall record the decision, comments, timestamp and authority in R20; only an approved effective version may update live records. | J131: Approver should review the checked change and its impact, then approve, return or reject it. A returned or rejected request should leave the current approved record unchanged. | K131: C05 | L131: R01, R17, R18, R20 | N131: C05, R01, R17, R18, R20 | O131: Must | P131: 1 - Foundation and Configuration | Q131: 6.1.5 | R131: Ready for Review
